Workbook

Sheet Cover
A2: FIN232a | B2: Mergers and Acquisitions Analysis Final Exam
A3: Professor | B3: Hamza Abdurezak
A4: Students | B4: Levan Kvinikadze

Sheet Assumptions
A2: HUBS Assumptions | J2: CRM Assumptions
A4: HUBS Assumptions Table From Financials | B4: 2026 | C4: 2027 | D4: 2028 | E4: 2029 | F4: 2030 | G4: Perpetuity | J4: CRM Assumptions Table From Financials | K4: 2026 | L4: 2027 | M4: 2028 | N4: 2029 | O4: 2030 | P4: Perpetuity
A5: Sales Growth | B5: ='HUBS Projection'!B24 -> 0.18 | C5: ='HUBS Projection'!C24 -> 0.16 | D5: ='HUBS Projection'!D24 -> 0.15 | E5: ='HUBS Projection'!E24 -> 0.14 | F5: ='HUBS Projection'!F24 -> 0.13 | G5: ='HUBS Projection'!G24 -> 0.035 | J5: Sales Growth | K5: ='CRM Projection'!B24 -> 0.095 | L5: ='CRM Projection'!C24 -> 0.105 | M5: ='CRM Projection'!D24 -> 0.11 | N5: ='CRM Projection'!E24 -> 0.1 | O5: ='CRM Projection'!F24 -> 0.09 | P5: ='CRM Projection'!G24 -> 0.035
A6: EBIT | B6: ='HUBS Projection'!B25 -> 0.05 | C6: ='HUBS Projection'!C25 -> 0.08 | D6: ='HUBS Projection'!D25 -> 0.11 | E6: ='HUBS Projection'!E25 -> 0.13 | F6: ='HUBS Projection'!F25 -> 0.15 | G6: ='HUBS Projection'!G25 -> 0.15 | J6: EBIT | K6: ='CRM Projection'!B25 -> 0.225 | L6: ='CRM Projection'!C25 -> 0.235 | M6: ='CRM Projection'!D25 -> 0.245 | N6: ='CRM Projection'!E25 -> 0.25 | O6: ='CRM Projection'!F25 -> 0.255 | P6: =O6 -> 0.255
A7: Depreciation and Amortization | B7: ='HUBS Projection'!$B$13 -> 0.041157041 | C7: ='HUBS Projection'!$B$13 -> 0.041157041 | D7: ='HUBS Projection'!$B$13 -> 0.041157041 | E7: ='HUBS Projection'!$B$13 -> 0.041157041 | F7: ='HUBS Projection'!$B$13 -> 0.041157041 | G7: ='HUBS Projection'!$B$13 -> 0.041157041 | J7: Depreciation and Amortization | K7: ='CRM Projection'!B26 -> 0.085 | L7: ='CRM Projection'!C26 -> 0.083 | M7: ='CRM Projection'!D26 -> 0.082 | N7: ='CRM Projection'!E26 -> 0.081 | O7: ='CRM Projection'!F26 -> 0.08 | P7: =O7 -> 0.08
A8: CAPEX | B8: ='HUBS Projection'!$B$17 -> 0.050916157 | C8: ='HUBS Projection'!$B$17 -> 0.050916157 | D8: ='HUBS Projection'!$B$17 -> 0.050916157 | E8: ='HUBS Projection'!$B$17 -> 0.050916157 | F8: ='HUBS Projection'!$B$17 -> 0.050916157 | G8: ='HUBS Projection'!$B$17 -> 0.050916157 | J8: CAPEX | K8: ='CRM Projection'!$B$17 -> 0.021060188 | L8: ='CRM Projection'!$B$17 -> 0.021060188 | M8: ='CRM Projection'!$B$17 -> 0.021060188 | N8: ='CRM Projection'!$B$17 -> 0.021060188 | O8: ='CRM Projection'!$B$17 -> 0.021060188 | P8: ='CRM Projection'!$B$17 -> 0.021060188
A9: NWC % of Sales | B9: ='HUBS Projection'!$B$21 -> -0.26729476 | C9: ='HUBS Projection'!$B$21 -> -0.26729476 | D9: ='HUBS Projection'!$B$21 -> -0.26729476 | E9: ='HUBS Projection'!$B$21 -> -0.26729476 | F9: ='HUBS Projection'!$B$21 -> -0.26729476 | G9: ='HUBS Projection'!$B$21 -> -0.26729476 | J9: NWC % of Sales | K9: ='CRM Projection'!$B$21 -> -0.36503072 | L9: ='CRM Projection'!$B$21 -> -0.36503072 | M9: ='CRM Projection'!$B$21 -> -0.36503072 | N9: ='CRM Projection'!$B$21 -> -0.36503072 | O9: ='CRM Projection'!$B$21 -> -0.36503072 | P9: ='CRM Projection'!$B$21 -> -0.36503072
A10: Tax Rate | B10: ='HUBS Projection'!$B$39 -> 0.25 | C10: ='HUBS Projection'!$B$39 -> 0.25 | D10: ='HUBS Projection'!$B$39 -> 0.25 | E10: ='HUBS Projection'!$B$39 -> 0.25 | F10: ='HUBS Projection'!$B$39 -> 0.25 | G10: ='HUBS Projection'!$B$39 -> 0.25 | J10: Tax Rate | K10: ='CRM Projection'!$B$39 -> 0.21 | L10: ='CRM Projection'!$B$39 -> 0.21 | M10: ='CRM Projection'!$B$39 -> 0.21 | N10: ='CRM Projection'!$B$39 -> 0.21 | O10: ='CRM Projection'!$B$39 -> 0.21 | P10: ='CRM Projection'!$B$39 -> 0.21
A12: WACC Assumptions | J12: WACC Assumptions
A13: Beta (Levered, 5-yr monthly vs. VOO) | B13: =Beta!N3 -> 1.4171699 | J13: Beta (Levered, 5-yr monthly vs. VOO) | K13: =Beta!N2 -> 1.2317362
A14: Market Risk Premium | B14: 0.06 | J14: Market Risk Premium | K14: =B14 -> 0.06
A15: 10-year Risk-Free Rate | B15: 0.0439 | J15: 10-year Risk-Free Rate | K15: =B15 -> 0.0439
A16: Cost of Equity | B16: =B15+B14*B13 -> 0.12893019 | J16: Cost of Equity | K16: =K15+K14*K13 -> 0.11780417
A17: Default Spread (near-zero debt) | B17: 0.0063 | J17: Default Spread (near-zero debt) | K17: ='CRM Projection'!B43 -> 0.0125
A18: Pre-Tax Cost of Debt | B18: =B17+B15 -> 0.0502 | J18: Pre-Tax Cost of Debt | K18: =K17+K15 -> 0.0564
A19: After-Tax Cost of Debt | B19: =B18*(1-G10) -> 0.03765 | J19: After-Tax Cost of Debt | K19: =K18*(1-P10) -> 0.044556
A20: Shares Outstanding (M) | B20: ='HUBS Projection'!B47 -> 52.74 | J20: Shares Outstanding (M) | K20: ='CRM Projection'!B47 -> 956
A21: Price Per Share ($) | B21: ='HUBS Projection'!B48 -> 262.06 | J21: Price Per Share ($) | K21: ='CRM Projection'!B48 -> 195.18
A22: Market Capitalization ($M) | B22: ='HUBS Projection'!B49 -> 13821.044 | J22: Market Capitalization ($M) | K22: ='CRM Projection'!B49 -> 186592.08
A23: Total Debt ($M) | B23: ='HUBS Projection'!B50 -> 39.703 | J23: Total Debt ($M) | K23: ='CRM Projection'!B50 -> 15262
A24: Weight of Equity | B24: ='HUBS Projection'!B53 -> 0.99713558 | J24: Weight of Equity | K24: ='CRM Projection'!B53 -> 0.92439093
A25: Weight of Debt | B25: ='HUBS Projection'!B52 -> 0.0028644199 | J25: Weight of Debt | K25: ='CRM Projection'!B52 -> 0.075609074
A26: WACC | B26: ='HUBS Projection'!B55 -> 0.12866873 | J26: WACC | K26: ='CRM Projection'!B55 -> 0.11226594
A27: Perpetuity Growth Rate | B27: =G5 -> 0.035 | J27: Perpetuity Growth Rate | K27: =P5 -> 0.035
A31: Merger Consequence Assumptions | J31: Deal Structure
A33: Assumption | B33: Value | K33: Option A | L33: Option B | M33: Option C | N33: Notes
A34: Proposed Acquisition Price ($M) | B34: 17000 | J34: Structure | K34: 100% Cash | L34: 50/50 | M34: 100% Stock | N34: Three financing scenarios analyzed.
A35: Ebit Contribution | B35: 0.45 | J35: Cash Deployed ($M) | K35: ='Combined Financials'!B21 -> 6565 | L35: ='Combined Financials'!C21 -> 6565 | M35: 0 | N35: Option A/B: cash less $3,000M reserve. Option C: full cash available.
A36: HUBS Book Value (Common Equity, $M) | B36: ='HUBS-US-BS'!K57 -> 2066.244 | J36: Stock Issued ($M) | K36: ='Combined Financials'!B22 -> 0 | L36: ='Combined Financials'!C22 -> 8500 | M36: ='Combined Financials'!D22 -> 17000 | N36: Valued at CRM share price of $195.18.
A37: Premium Over Book Value ($M) | B37: =B34-B36 -> 14933.756 | J37: New Debt Required ($M) | K37: ='Combined Financials'!B23 -> 10435 | L37: ='Combined Financials'!C23 -> 1935 | M37: ='Combined Financials'!D23 -> 0 | N37: Residual after cash and stock.
A38: % of Premium to Identifiable Intangibles (PPA) | B38: 0.35 | J38: New Shares Issued (M) | K38: ='Combined Financials'!B24 -> 0 | L38: ='Combined Financials'!C24 -> 43.549544 | M38: ='Combined Financials'!D24 -> 87.099088 | N38: Stock / CRM price per share.
A39: Intangibles Amortization Period (Years) | B39: 7 | J39: CRM Available Cash ($M) | K39: ='Combined Financials'!B19 -> 9565 | L39: ='Combined Financials'!C19 -> 9565 | M39: ='Combined Financials'!D19 -> 9565 | N39: Source: FactSet CRM-US-BS.
A40: Annual PPA Amortization ($M) | B40: ='Combined Financials'!B32 -> 746.6878 | J40: Minimum Cash Reserve ($M) | K40: ='Combined Financials'!B20 -> 3000 | L40: ='Combined Financials'!C20 -> 3000 | M40: ='Combined Financials'!D20 -> 0 | N40: Management prudence floor for Options A/B; waived for all-stock Option C.
A45: Synergy Assumption
B46: 2026 | C46: 2027 | D46: 2028 | E46: 2029 | F46: 2030 | G46: Run-Rate
A47: Revenue Synergies ($M) | B47: 50 | C47: 130 | D47: 200 | E47: 200 | F47: 200 | G47: 200
A48: Cost Synergies ($M) | B48: 62.5 | C48: 162.5 | D48: 250 | E48: 250 | F48: 250 | G48: 250
A49: Revenue Synergy Incremental EBIT Margin | B49: 0.45 | C49: 0.45 | D49: 0.45 | E49: 0.45 | F49: 0.45 | G49: 0.45

Sheet DCF Summary
A1: DISCOUNTED CASH FLOW ANALYSIS — HubSpot (HUBS) & Salesforce (CRM)
A2: HubSpot, Inc. (HUBS) — Standalone DCF | H2: Salesforce, Inc. (CRM) — Standalone DCF
A3: Metric ($M) | B3: 2026 | C3: 2027 | D3: 2028 | E3: 2029 | F3: 2030 | H3: Metric ($M) | I3: 2026 | J3: 2027 | K3: 2028 | L3: 2029 | M3: 2030
A4: Revenue | B4: ='HUBS Projection'!B59 -> 3694.8679 | C4: ='HUBS Projection'!C59 -> 4286.0468 | D4: ='HUBS Projection'!D59 -> 4928.9538 | E4: ='HUBS Projection'!E59 -> 5619.0073 | F4: ='HUBS Projection'!F59 -> 6349.4783 | H4: Revenue | I4: ='CRM Projection'!B59 -> 45469.875 | J4: ='CRM Projection'!C59 -> 50244.212 | K4: ='CRM Projection'!D59 -> 55771.075 | L4: ='CRM Projection'!E59 -> 61348.183 | M4: ='CRM Projection'!F59 -> 66869.519
A5: EBIT | B5: ='HUBS Projection'!B60 -> 184.7434 | C5: ='HUBS Projection'!C60 -> 342.88374 | D5: ='HUBS Projection'!D60 -> 542.18492 | E5: ='HUBS Projection'!E60 -> 730.47095 | F5: ='HUBS Projection'!F60 -> 952.42174 | H5: EBIT | I5: ='CRM Projection'!B60 -> 10230.722 | J5: ='CRM Projection'!C60 -> 11807.39 | K5: ='CRM Projection'!D60 -> 13663.913 | L5: ='CRM Projection'!E60 -> 15337.046 | M5: ='CRM Projection'!F60 -> 17051.727
A6: NOPAT | B6: ='HUBS Projection'!B61 -> 138.55755 | C6: ='HUBS Projection'!C61 -> 257.16281 | D6: ='HUBS Projection'!D61 -> 406.63869 | E6: ='HUBS Projection'!E61 -> 547.85322 | F6: ='HUBS Projection'!F61 -> 714.31631 | H6: NOPAT | I6: ='CRM Projection'!B61 -> 8082.2703 | J6: ='CRM Projection'!C61 -> 9327.8379 | K6: ='CRM Projection'!D61 -> 10794.492 | L6: ='CRM Projection'!E61 -> 12116.266 | M6: ='CRM Projection'!F61 -> 13470.865
A7: (+) D&A | B7: ='HUBS Projection'!B62 -> 152.06983 | C7: ='HUBS Projection'!C62 -> 176.401 | D7: ='HUBS Projection'!D62 -> 202.86116 | E7: ='HUBS Projection'!E62 -> 231.26172 | F7: ='HUBS Projection'!F62 -> 261.32574 | H7: (+) D&A | I7: ='CRM Projection'!B62 -> 3864.9394 | J7: ='CRM Projection'!C62 -> 4170.2696 | K7: ='CRM Projection'!D62 -> 4573.2282 | L7: ='CRM Projection'!E62 -> 4969.2028 | M7: ='CRM Projection'!F62 -> 5349.5615
A8: (–) CAPEX | B8: ='HUBS Projection'!B63 -> 188.12848 | C8: ='HUBS Projection'!C63 -> 218.22903 | D8: ='HUBS Projection'!D63 -> 250.96339 | E8: ='HUBS Projection'!E63 -> 286.09826 | F8: ='HUBS Projection'!F63 -> 323.29103 | H8: (–) CAPEX | I8: ='CRM Projection'!B63 -> 957.60412 | J8: ='CRM Projection'!C63 -> 1058.1526 | K8: ='CRM Projection'!D63 -> 1174.5493 | L8: ='CRM Projection'!E63 -> 1292.0043 | M8: ='CRM Projection'!F63 -> 1408.2847
A9: (–) Δ NWC | B9: ='HUBS Projection'!B65 -> -79.607818 | C9: ='HUBS Projection'!C65 -> -158.01901 | D9: ='HUBS Projection'!D65 -> -171.84567 | E9: ='HUBS Projection'!E65 -> -184.44769 | F9: ='HUBS Projection'!F65 -> -195.25106 | H9: (–) Δ NWC | I9: ='CRM Projection'!B65 -> -884.90125 | J9: ='CRM Projection'!C65 -> -1742.7796 | K9: ='CRM Projection'!D65 -> -2017.4749 | L9: ='CRM Projection'!E65 -> -2035.8156 | M9: ='CRM Projection'!F65 -> -2015.4574
A10: Free Cash Flow | B10: ='HUBS Projection'!B66 -> 182.10672 | C10: ='HUBS Projection'!C66 -> 373.35379 | D10: ='HUBS Projection'!D66 -> 530.38213 | E10: ='HUBS Projection'!E66 -> 677.46436 | F10: ='HUBS Projection'!F66 -> 847.60207 | H10: Free Cash Flow | I10: ='CRM Projection'!B66 -> 11874.507 | J10: ='CRM Projection'!C66 -> 14182.735 | K10: ='CRM Projection'!D66 -> 16210.645 | L10: ='CRM Projection'!E66 -> 17829.28 | M10: ='CRM Projection'!F66 -> 19427.599
A11: PV of FCF | B11: ='HUBS Projection'!B67 -> 161.34648 | C11: ='HUBS Projection'!C67 -> 293.08094 | D11: ='HUBS Projection'!D67 -> 368.88365 | E11: ='HUBS Projection'!E67 -> 417.4654 | F11: ='HUBS Projection'!F67 -> 462.76398 | H11: PV of FCF | I11: ='CRM Projection'!B67 -> 10675.96 | J11: ='CRM Projection'!C67 -> 11464.172 | K11: ='CRM Projection'!D67 -> 11780.789 | L11: ='CRM Projection'!E67 -> 11649.284 | M11: ='CRM Projection'!F67 -> 11412.372
A12: Valuation Bridge | H12: Valuation Bridge
A13: Sum of PV (FCFs) | B13: ='HUBS Projection'!B68 -> 1703.5405 | H13: Sum of PV (FCFs) | I13: ='CRM Projection'!B68 -> 56982.578
A14: Terminal Value | B14: ='HUBS Projection'!B69 -> 9365.6461 | H14: Terminal Value | I14: ='CRM Projection'!B69 -> 260238.39
A15: PV of Terminal Value | B15: ='HUBS Projection'!B70 -> 5113.3472 | H15: PV of Terminal Value | I15: ='CRM Projection'!B70 -> 152872.08
A16: Enterprise Value (EV) | B16: ='HUBS Projection'!B71 -> 6816.8877 | H16: Enterprise Value (EV) | I16: ='CRM Projection'!B71 -> 209854.66
A19: KEY ASSUMPTIONS — Side-by-Side Comparison
A20: Assumption | B20: HUBS | C20: CRM
A21: WACC | B21: ='HUBS Projection'!B55 -> 0.12866873 | C21: ='CRM Projection'!B55 -> 0.11226594
A22: Beta (Levered) | B22: ='HUBS Projection'!B29 -> 1.4171699 | C22: ='CRM Projection'!B29 -> 1.2317362
A23: Risk-Free Rate | B23: ='HUBS Projection'!B31 -> 0.0439 | C23: ='CRM Projection'!B31 -> 0.0439
A24: Market Risk Premium | B24: ='HUBS Projection'!B30 -> 0.06 | C24: ='CRM Projection'!B30 -> 0.06
A25: Cost of Equity | B25: ='HUBS Projection'!B32 -> 0.12893019 | C25: ='CRM Projection'!B32 -> 0.11780417
A26: After-Tax Cost of Debt | B26: ='HUBS Projection'!B45 -> 0.03765 | C26: ='CRM Projection'!B45 -> 0.044556
A27: Tax Rate | B27: ='HUBS Projection'!B39 -> 0.25 | C27: ='CRM Projection'!B39 -> 0.21
A28: Perpetuity Growth Rate | B28: ='HUBS Projection'!G24 -> 0.035 | C28: ='CRM Projection'!G24 -> 0.035
A31: FOOTBALL FIELD — Valuation Summary (To Be Completed After Comps Analysis)
A32: Valuation Method | B32: Low ($M) | C32: Midpoint ($M) | D32: High ($M) | E32: Implied EV/Rev (Low) | F32: Implied EV/Rev (High)
A33: DCF (Standalone) | B33: ='HUBS Projection'!D78 -> 5847.9742 | C33: =$B$16 -> 6816.8877 | D33: ='HUBS Projection'!F76 -> 8148.9157 | E33: =B16/'HUBS Projection'!B59 -> 1.8449611 | F33: =B16/'HUBS Projection'!B59 -> 1.8449611
A34: Comparable Company Analysis | B34: ='Trading Comps'!F21 -> 12550.181 | C34: ='Trading Comps'!G21 -> 14819.436 | D34: ='Trading Comps'!H21 -> 18600.649 | E34: ='Trading Comps'!C18 -> 4.206936 | F34: ='Trading Comps'!E18 -> 5.034185
A35: Precedent Transactions | B35: ='Transaction Comps'!G17 -> 21605.584 | C35: ='Transaction Comps'!H17 -> 28669.67 | D35: ='Transaction Comps'!I17 -> 32514.838
A36: Proposed Bid Range | B36: =AVERAGE(B33:B35) -> 13334.58 | C36: =AVERAGE(C33:C35) -> 16768.665 | D36: =AVERAGE(D33:D35) -> 19754.801

Sheet Combined Financials
A2: Purchase Price | B2: =Assumptions!B34 -> 17000
A3: EBIT Contribution | B3: =Assumptions!B35 -> 0.45 | C3: <-- 45% incremental EBIT margin, below the 50–70% SaaS benchmark, reflecting additional integration and onboarding costs from combining two distinct product platforms.
A4: HUBS Book Value | B4: =Assumptions!B36 -> 2066.244
A5: Premium allocated to identifiable intangibles | B5: =Assumptions!B38 -> 0.35
A6: Premium Amortization (Years) | B6: =Assumptions!B39 -> 7
A7: CRM Total Cash Available | B7: ='CRM-US-BS'!K11*1000 -> 9565
A8: Minimum Cash Reserve Required | B8: 3000
A9: CRM Shares Outstanding | B9: ='CRM Projection'!B47 -> 956
A10: Pre-Tax Cost of Debt | B10: ='CRM Projection'!B44 -> 0.0564
A11: Tax Rate | B11: ='CRM Projection'!B39 -> 0.21
B13: 2026 | C13: 2027 | D13: 2028 | E13: 2029 | F13: 2030
A14: Revenue Synergies | B14: 50 | C14: 130 | D14: 200 | E14: 200 | F14: 200
A15: Cost Synergies | B15: 62.5 | C15: 162.5 | D15: 250 | E15: 250 | F15: 250
B17: Option A | C17: Option B | D17: Option C
B18: 100% cash | C18: 50/50 cash&stock | D18: 100% stock
A19: Total Cash Available | B19: =$B$7 -> 9565 | C19: =$B$7 -> 9565 | D19: =$B$7 -> 9565
A20: Minimum Cash reserve | B20: =$B$8 -> 3000 | C20: =$B$8 -> 3000 | D20: 0
A21: Usable Cash deployed | B21: =B19-B20 -> 6565 | C21: =C19-C20 -> 6565 | D21: 0
A22: Stock Issued ($) | B22: 0 | C22: =B28/2 -> 8500 | D22: =B28 -> 17000
A23: New Debt Required | B23: =B2-B21 -> 10435 | C23: =B2-C21-C22 -> 1935 | D23: 0
A24: New Shares Issued | B24: 0 | C24: =C22/Beta!B4 -> 43.549544 | D24: =D22/Beta!B4 -> 87.099088
A25: Total diluted shares (M) | B25: =B24+$B$9 -> 956 | C25: =C24+$B$9 -> 999.54954 | D25: =D24+$B$9 -> 1043.0991
A26: Gross Interest Expense | B26: =B23*$B$10 -> 588.534 | C26: =C23*$B$10 -> 109.134 | D26: =D23*$B$10 -> 0
A28: Purchase Price | B28: =B2 -> 17000
A29: HUBS Book Value | B29: =B4 -> 2066.244
A30: Premium Over Book Value | B30: =B28-B29 -> 14933.756
A31: 35% to Intangibles | B31: =B30*B5 -> 5226.8146 | C31: <-- Premium allocated to identifiable intangibles (Customer customer relationships, developed technology, trade names)
A32: Amortized over 7 years | B32: =B31/B6 -> 746.6878 | C32: <-- amortized over 7 years per ASC 805 (Business Combinations). | H32: The 7-year useful life is consistent with Salesforce's weighted average intangible amortization period applied in prior large acquisitions including Tableau ($15.7B, 2019) and Slack ($27.7B, 2021).
B34: 2026 | C34: 2027 | D34: 2028 | E34: 2029 | F34: 2030
A35: Combined Revenue | B35: =B14+'HUBS Projection'!B59+'CRM Projection'!B59 -> 49214.743 | C35: =C14+'HUBS Projection'!C59+'CRM Projection'!C59 -> 54660.259 | D35: =D14+'HUBS Projection'!D59+'CRM Projection'!D59 -> 60900.029 | E35: =E14+'HUBS Projection'!E59+'CRM Projection'!E59 -> 67167.19 | F35: =F14+'HUBS Projection'!F59+'CRM Projection'!F59 -> 73418.997
A36: CRM EBIT | B36: ='CRM Projection'!B60 -> 10230.722 | C36: ='CRM Projection'!C60 -> 11807.39 | D36: ='CRM Projection'!D60 -> 13663.913 | E36: ='CRM Projection'!E60 -> 15337.046 | F36: ='CRM Projection'!F60 -> 17051.727
A37: HUBS EBIT | B37: ='HUBS Projection'!B60 -> 184.7434 | C37: ='HUBS Projection'!C60 -> 342.88374 | D37: ='HUBS Projection'!D60 -> 542.18492 | E37: ='HUBS Projection'!E60 -> 730.47095 | F37: ='HUBS Projection'!F60 -> 952.42174
A38: Revenue Synergies EBIT contribution | B38: =B14*$B$3 -> 22.5 | C38: =C14*$B$3 -> 58.5 | D38: =D14*$B$3 -> 90 | E38: =E14*$B$3 -> 90 | F38: =F14*$B$3 -> 90
A39: Cost Synergies | B39: =B15 -> 62.5 | C39: =C15 -> 162.5 | D39: =D15 -> 250 | E39: =E15 -> 250 | F39: =F15 -> 250
A40: Purchase Price Amortization | B40: =-$B$32 -> -746.6878 | C40: =-$B$32 -> -746.6878 | D40: =-$B$32 -> -746.6878 | E40: =-$B$32 -> -746.6878 | F40: =-$B$32 -> -746.6878
A41: Combined EBIT | B41: =SUM(B36:B40) -> 9753.7775 | C41: =SUM(C36:C40) -> 11624.586 | D41: =SUM(D36:D40) -> 13799.411 | E41: =SUM(E36:E40) -> 15660.829 | F41: =SUM(F36:F40) -> 17597.461
A42: Combined D&A | B42: ='CRM Projection'!B62+'HUBS Projection'!B62+$B$32 -> 4763.697 | C42: ='CRM Projection'!C62+'HUBS Projection'!C62+$B$32 -> 5093.3584 | D42: ='CRM Projection'!D62+'HUBS Projection'!D62+$B$32 -> 5522.7771 | E42: ='CRM Projection'!E62+'HUBS Projection'!E62+$B$32 -> 5947.1523 | F42: ='CRM Projection'!F62+'HUBS Projection'!F62+$B$32 -> 6357.5751
A43: Combined EBITDA | B43: =SUM(B41:B42) -> 14517.474 | C43: =SUM(C41:C42) -> 16717.944 | D43: =SUM(D41:D42) -> 19322.188 | E43: =SUM(E41:E42) -> 21607.981 | F43: =SUM(F41:F42) -> 23955.036
A45: Option A | B45: 2026 | C45: 2027 | D45: 2028 | E45: 2029 | F45: 2030
A46: Pro-forma Combined EBIT | B46: =B41 -> 9753.7775 | C46: =C41 -> 11624.586 | D46: =D41 -> 13799.411 | E46: =E41 -> 15660.829 | F46: =F41 -> 17597.461
A47: Gross Interest Expense | B47: =B107 -> 912.534 | C47: =C107 -> 353.4848 | D47: =D107 -> 324 | E47: =E107 -> 324 | F47: =F107 -> 324
A48: Pretax Income | B48: =B46-B47 -> 8841.2435 | C48: =C46-C47 -> 11271.101 | D48: =D46-D47 -> 13475.411 | E48: =E46-E47 -> 15336.829 | F48: =F46-F47 -> 17273.461
A49: Combined Net Income | B49: =B48*(1-$B$11) -> 6984.5823 | C49: =C48*(1-$B$11) -> 8904.1697 | D49: =D48*(1-$B$11) -> 10645.574 | E49: =E48*(1-$B$11) -> 12116.095 | F49: =F48*(1-$B$11) -> 13646.034
A50: Divided by diluted shares | B50: =B49/$B$25 -> 7.3060485 | C50: =C49/$B$25 -> 9.3139851 | D50: =D49/$B$25 -> 11.135538 | E50: =E49/$B$25 -> 12.673739 | F50: =F49/$B$25 -> 14.274095
A51: CRM Standalone EPS | B51: =('CRM Projection'!B60-$B$78)*(1-$B$11)/$B$25 -> 8.186517 | C51: =('CRM Projection'!C60-$B$78)*(1-$B$11)/$B$25 -> 9.4894121 | D51: =('CRM Projection'!D60-$B$78)*(1-$B$11)/$B$25 -> 11.023569 | E51: =('CRM Projection'!E60-$B$78)*(1-$B$11)/$B$25 -> 12.406178 | F51: =('CRM Projection'!F60-$B$78)*(1-$B$11)/$B$25 -> 13.823122
A52: Accretion/(Dilution) % | B52: =B50/B51-1 -> -0.10755106 | C52: =C50/C51-1 -> -0.018486602 | D52: =D50/D51-1 -> 0.010157271 | E52: =E50/E51-1 -> 0.021566787 | F52: =F50/F51-1 -> 0.032624512
A54: Option B | B54: 2026 | C54: 2027 | D54: 2028 | E54: 2029 | F54: 2030
A55: Pro-forma Combined EBIT | B55: =B41 -> 9753.7775 | C55: =C41 -> 11624.586 | D55: =D41 -> 13799.411 | E55: =E41 -> 15660.829 | F55: =F41 -> 17597.461
A56: Gross Interest Expense | B56: =$C$26+B78 -> 433.134 | C56: =B56 -> 433.134 | D56: =C56 -> 433.134 | E56: =D56 -> 433.134 | F56: =E56 -> 433.134
A57: Pretax Income | B57: =B55-B56 -> 9320.6435 | C57: =C55-C56 -> 11191.452 | D57: =D55-D56 -> 13366.277 | E57: =E55-E56 -> 15227.695 | F57: =F55-F56 -> 17164.327
A58: Combined Net Income | B58: =B57*(1-$B$11) -> 7363.3083 | C58: =C57*(1-$B$11) -> 8841.2469 | D58: =D57*(1-$B$11) -> 10559.358 | E58: =E57*(1-$B$11) -> 12029.879 | F58: =F57*(1-$B$11) -> 13559.819
A59: Divided by diluted shares | B59: =B58/$C$25 -> 7.3666267 | C59: =C58/$C$25 -> 8.8452313 | D59: =D58/$C$25 -> 10.564117 | E59: =E58/$C$25 -> 12.0353 | F59: =F58/$C$25 -> 13.565929
A60: CRM Standalone EPS | B60: =B51 -> 8.186517 | C60: =C51 -> 9.4894121 | D60: =D51 -> 11.023569 | E60: =E51 -> 12.406178 | F60: =F51 -> 13.823122
A61: Accretion/(Dilution) % | B61: =B59/B60-1 -> -0.1001513 | C61: =C59/C60-1 -> -0.067884164 | D61: =D59/D60-1 -> -0.041679015 | E61: =E59/E60-1 -> -0.029894592 | F61: =F59/F60-1 -> -0.018605967
A63: Option C | B63: 2026 | C63: 2027 | D63: 2028 | E63: 2029 | F63: 2030
A64: Pro-forma Combined EBIT | B64: =B41 -> 9753.7775 | C64: =C41 -> 11624.586 | D64: =D41 -> 13799.411 | E64: =E41 -> 15660.829 | F64: =F41 -> 17597.461
A65: Gross Interest Expense | B65: =$D$26 -> 0 | C65: =$D$26 -> 0 | D65: =$D$26 -> 0 | E65: =$D$26 -> 0 | F65: =$D$26 -> 0
A66: Pretax Income | B66: =B64-B65 -> 9753.7775 | C66: =C64-C65 -> 11624.586 | D66: =D64-D65 -> 13799.411 | E66: =E64-E65 -> 15660.829 | F66: =F64-F65 -> 17597.461
A67: Combined Net Income | B67: =B66*(1-$B$11) -> 7705.4842 | C67: =C66*(1-$B$11) -> 9183.4227 | D67: =D66*(1-$B$11) -> 10901.534 | E67: =E66*(1-$B$11) -> 12372.055 | F67: =F66*(1-$B$11) -> 13901.994
A68: Divided by diluted shares | B68: =B67/$D$25 -> 7.3871066 | C68: =C67/$D$25 -> 8.8039793 | D68: =D67/$D$25 -> 10.451101 | E68: =E67/$D$25 -> 11.860862 | F68: =F67/$D$25 -> 13.327588
A69: CRM Standalone EPS | B69: =B60 -> 8.186517 | C69: =C60 -> 9.4894121 | D69: =D60 -> 11.023569 | E69: =E60 -> 12.406178 | F69: =F60 -> 13.823122
A70: Accretion/(Dilution) % | B70: =B68/B69-1 -> -0.097649634 | C70: =C68/C69-1 -> -0.072231326 | D70: =D68/D69-1 -> -0.051931208 | E70: =E68/E69-1 -> -0.043955156 | F70: =F68/F69-1 -> -0.035848228
A74: COMBINED FINANCIAL STATEMENTS -- OPTION A (100% CASH)
A76: Additional Assumptions
B77: 2026 | C77: 2027 | D77: 2028 | E77: 2029 | F77: 2030
A78: CRM Standalone Gross Interest ($M) | B78: 324 | C78: 324 | D78: 324 | E78: 324 | F78: 324
A79: CRM Dividend per Share ($) | B79: 1.731 | C79: =B79*(1+$B$80) -> 1.80024 | D79: =C79*(1+$B$80) -> 1.8722496 | E79: =D79*(1+$B$80) -> 1.9471396 | F79: =E79*(1+$B$80) -> 2.0250252
A80: Dividend Growth Rate | B80: 0.04
A81: Opening Cash at Deal Close ($M) | B81: 4704 | C81: <-- CRM $9,565 - $6,565 used + HUBS $1,704
A82: CRM+HUBS Existing Debt ($M) | B82: 15524 | C82: <-- CRM $15,262 + HUBS $262, held flat
A83: Opening Equity at Close ($M) | B83: 59142
A85: Combined Income Statement ($M)
B86: 2026 | C86: 2027 | D86: 2028 | E86: 2029 | F86: 2030
A87: CRM Revenue | B87: ='CRM Projection'!B59 -> 45469.875 | C87: ='CRM Projection'!C59 -> 50244.212 | D87: ='CRM Projection'!D59 -> 55771.075 | E87: ='CRM Projection'!E59 -> 61348.183 | F87: ='CRM Projection'!F59 -> 66869.519
A88: HUBS Revenue | B88: ='HUBS Projection'!B59 -> 3694.8679 | C88: ='HUBS Projection'!C59 -> 4286.0468 | D88: ='HUBS Projection'!D59 -> 4928.9538 | E88: ='HUBS Projection'!E59 -> 5619.0073 | F88: ='HUBS Projection'!F59 -> 6349.4783
A89: Revenue Synergies | B89: =B14 -> 50 | C89: =C14 -> 130 | D89: =D14 -> 200 | E89: =E14 -> 200 | F89: =F14 -> 200
A90: Total Revenue | B90: =SUM(B87:B89) -> 49214.743 | C90: =SUM(C87:C89) -> 54660.259 | D90: =SUM(D87:D89) -> 60900.029 | E90: =SUM(E87:E89) -> 67167.19 | F90: =SUM(F87:F89) -> 73418.997
A92: CRM EBIT | B92: ='CRM Projection'!B60 -> 10230.722 | C92: ='CRM Projection'!C60 -> 11807.39 | D92: ='CRM Projection'!D60 -> 13663.913 | E92: ='CRM Projection'!E60 -> 15337.046 | F92: ='CRM Projection'!F60 -> 17051.727
A93: HUBS EBIT | B93: ='HUBS Projection'!B60 -> 184.7434 | C93: ='HUBS Projection'!C60 -> 342.88374 | D93: ='HUBS Projection'!D60 -> 542.18492 | E93: ='HUBS Projection'!E60 -> 730.47095 | F93: ='HUBS Projection'!F60 -> 952.42174
A94: Revenue Synergy EBIT | B94: =B89*$B$3 -> 22.5 | C94: =C89*$B$3 -> 58.5 | D94: =D89*$B$3 -> 90 | E94: =E89*$B$3 -> 90 | F94: =F89*$B$3 -> 90
A95: Cost Synergies | B95: =B15 -> 62.5 | C95: =C15 -> 162.5 | D95: =D15 -> 250 | E95: =E15 -> 250 | F95: =F15 -> 250
A96: PPA Amortization | B96: =-$B$32 -> -746.6878 | C96: =-$B$32 -> -746.6878 | D96: =-$B$32 -> -746.6878 | E96: =-$B$32 -> -746.6878 | F96: =-$B$32 -> -746.6878
A97: Combined EBIT | B97: =SUM(B92:B96) -> 9753.7775 | C97: =SUM(C92:C96) -> 11624.586 | D97: =SUM(D92:D96) -> 13799.411 | E97: =SUM(E92:E96) -> 15660.829 | F97: =SUM(F92:F96) -> 17597.461
A99: CRM D&A | B99: ='CRM Projection'!B62 -> 3864.9394 | C99: ='CRM Projection'!C62 -> 4170.2696 | D99: ='CRM Projection'!D62 -> 4573.2282 | E99: ='CRM Projection'!E62 -> 4969.2028 | F99: ='CRM Projection'!F62 -> 5349.5615
A100: HUBS D&A | B100: ='HUBS Projection'!B62 -> 152.06983 | C100: ='HUBS Projection'!C62 -> 176.401 | D100: ='HUBS Projection'!D62 -> 202.86116 | E100: ='HUBS Projection'!E62 -> 231.26172 | F100: ='HUBS Projection'!F62 -> 261.32574
A101: PPA Amortization (non-cash add-back) | B101: =$B$32 -> 746.6878 | C101: =$B$32 -> 746.6878 | D101: =$B$32 -> 746.6878 | E101: =$B$32 -> 746.6878 | F101: =$B$32 -> 746.6878
A102: Total D&A | B102: =SUM(B99:B101) -> 4763.697 | C102: =SUM(C99:C101) -> 5093.3584 | D102: =SUM(D99:D101) -> 5522.7771 | E102: =SUM(E99:E101) -> 5947.1523 | F102: =SUM(F99:F101) -> 6357.5751
A103: Combined EBITDA | B103: =B97+B102 -> 14517.474 | C103: =C97+C102 -> 16717.944 | D103: =D97+D102 -> 19322.188 | E103: =E97+E102 -> 21607.981 | F103: =F97+F102 -> 23955.036
A105: CRM Standalone Gross Interest | B105: =B78 -> 324 | C105: =C78 -> 324 | D105: =D78 -> 324 | E105: =E78 -> 324 | F105: =F78 -> 324
A106: Acquisition Debt Interest | B106: =B122 -> 588.534 | C106: =C122 -> 29.484802 | D106: =D122 -> 0 | E106: =E122 -> 0 | F106: =F122 -> 0
A107: Total Interest Expense | B107: =B105+B106 -> 912.534 | C107: =C105+C106 -> 353.4848 | D107: =D105+D106 -> 324 | E107: =E105+E106 -> 324 | F107: =F105+F106 -> 324
A108: Pretax Income | B108: =B97-B107 -> 8841.2435 | C108: =C97-C107 -> 11271.101 | D108: =D97-D107 -> 13475.411 | E108: =E97-E107 -> 15336.829 | F108: =F97-F107 -> 17273.461
A109: Taxes (21%) | B109: =B108*$B$11 -> 1856.6611 | C109: =C108*$B$11 -> 2366.9312 | D109: =D108*$B$11 -> 2829.8362 | E109: =E108*$B$11 -> 3220.7341 | F109: =F108*$B$11 -> 3627.4269
A110: Combined Net Income | B110: =B108-B109 -> 6984.5823 | C110: =C108-C109 -> 8904.1697 | D110: =D108-D109 -> 10645.574 | E110: =E108-E109 -> 12116.095 | F110: =F108-F109 -> 13646.034
A112: Diluted Shares Outstanding (M) | B112: =$B$9 -> 956 | C112: =$B$9 -> 956 | D112: =$B$9 -> 956 | E112: =$B$9 -> 956 | F112: =$B$9 -> 956
A113: Combined EPS ($) | B113: =B110/B112 -> 7.3060485 | C113: =C110/C112 -> 9.3139851 | D113: =D110/D112 -> 11.135538 | E113: =E110/E112 -> 12.673739 | F113: =F110/F112 -> 14.274095
A114: CRM Standalone EPS ($) | B114: =B51 -> 8.186517 | C114: =C51 -> 9.4894121 | D114: =D51 -> 11.023569 | E114: =E51 -> 12.406178 | F114: =F51 -> 13.823122
A115: Accretion / (Dilution) % | B115: =(B113-B114)/B114 -> -0.10755106 | C115: =(C113-C114)/C114 -> -0.018486602 | D115: =(D113-D114)/D114 -> 0.010157271 | E115: =(E113-E114)/E114 -> 0.021566787 | F115: =(F113-F114)/F114 -> 0.032624512
A119: Acquisition Debt Schedule ($M)
B120: 2026 | C120: 2027 | D120: 2028 | E120: 2029 | F120: 2030
...

Sheet Trading Comps
A2: Comparable Company Analysis
D3: Revenue | F3: EV/Revenue | G3: EV/EBITDA | I3: EBITDA Margin
A4: Company | B4: Ticker | C4: EV($M) | D4: FY1 ($M) | E4: FY2 ($M) | F4: FY1 (x) | G4: FY1 (x) | H4: FY2 (x) | I4: FY1 (%) | J4: FY2 (%)
A5: Okta A | B5: OKTA | C5: ='Raw Comps'!F20 -> 12522.567 | D5: ='Raw Comps'!D6 -> 3183.3779 | E5: ='Raw Comps'!E6 -> 3483.6277 | F5: ='Raw Comps'!J20 -> 4.29002 | G5: =C5/'Raw Comps'!F6 -> 14.934707 | H5: =C5/'Raw Comps'!H6 -> 13.024704 | I5: ='Raw Comps'!G6 -> 26.339558 | J5: ='Raw Comps'!I6 -> 27.599028
A6: Roku A | B6: ROKU | C6: ='Raw Comps'!F21 -> 12774.137 | D6: ='Raw Comps'!D7 -> 5502.4629 | E6: ='Raw Comps'!E7 -> 6159.3965 | F6: ='Raw Comps'!J21 -> 2.696529 | G6: =C6/'Raw Comps'!F7 -> 19.904779 | H6: =C6/'Raw Comps'!H7 -> 15.133554 | I6: ='Raw Comps'!G7 -> 11.663183 | J6: ='Raw Comps'!I7 -> 13.704163
A7: Tyler Technologies | B7: TYL | C7: ='Raw Comps'!F22 -> 14273.045 | D7: ='Raw Comps'!D8 -> 2531.1392 | E7: ='Raw Comps'!E8 -> 2777.762 | F7: ='Raw Comps'!J22 -> 6.119624 | G7: =C7/'Raw Comps'!F8 -> 19.331432 | H7: =C7/'Raw Comps'!H8 -> 16.932541 | I7: ='Raw Comps'!G8 -> 29.17001 | J7: ='Raw Comps'!I8 -> 30.34586
A8: Gen Digital | B8: GEN | C8: ='Raw Comps'!F23 -> 19493.449 | D8: ='Raw Comps'!D9 -> 4960.8027 | E8: ='Raw Comps'!E9 -> 5240.9624 | F8: ='Raw Comps'!J23 -> 4.123852 | G8: =C8/'Raw Comps'!F9 -> 7.8562476 | H8: =C8/'Raw Comps'!H9 -> 7.3979008 | I8: ='Raw Comps'!G9 -> 50.017452 | J8: ='Raw Comps'!I9 -> 50.276978
A9: Jack Henry & Associates | B9: JKHY | C9: ='Raw Comps'!F24 -> 11414.654 | D9: ='Raw Comps'!D10 -> 2519.6321 | E9: ='Raw Comps'!E10 -> 2677.5244 | F9: ='Raw Comps'!J24 -> 4.631572 | G9: =C9/'Raw Comps'!F10 -> 14.072705 | H9: =C9/'Raw Comps'!H10 -> 13.12515 | I9: ='Raw Comps'!G10 -> 32.192005 | J9: ='Raw Comps'!I10 -> 32.480675
A10: Dynatrace | B10: DT | C10: ='Raw Comps'!F25 -> 10503.002 | D10: ='Raw Comps'!D11 -> 2007.6473 | E10: ='Raw Comps'!E11 -> 2304.9592 | F10: ='Raw Comps'!J25 -> 5.436798 | G10: =C10/'Raw Comps'!F11 -> 17.291853 | H10: =C10/'Raw Comps'!H11 -> 14.753517 | I10: ='Raw Comps'!G11 -> 30.254116 | J10: ='Raw Comps'!I11 -> 30.8855
A11: Trimble | B11: TRMB | C11: ='Raw Comps'!F26 -> 16364.767 | D11: ='Raw Comps'!D12 -> 3866.2544 | E11: ='Raw Comps'!E12 -> 4182.0425 | F11: ='Raw Comps'!J26 -> 4.561862 | G11: =C11/'Raw Comps'!F12 -> 14.23491 | H11: =C11/'Raw Comps'!H12 -> 13.073736 | I11: ='Raw Comps'!G12 -> 29.734776 | J11: ='Raw Comps'!I12 -> 29.93103
A12: Mean | F12: =AVERAGE(F5:F11) -> 4.5514653 | G12: =AVERAGE(G5:G11) -> 15.375233 | H12: =AVERAGE(H5:H11) -> 13.348729
A13: Median | F13: =MEDIAN(F5:F11) -> 4.561862 | G13: =MEDIAN(G5:G11) -> 14.934707 | H13: =MEDIAN(H5:H11) -> 13.12515
A16: Implied Enterprise Value for HubSpot
A17: Valuation Method | B17: Metric | C17: Multiple Low | D17: Multiple Mid | E17: Multiple High | F17: Implied EV Low | G17: Implied EV Mid | H17: Implied EV High
A18: EV / Revenue | B18: ='HUBS Projection'!B59 -> 3694.8679 | C18: =_xlfn.PERCENTILE.INC(F5:F11,0.25) -> 4.206936 | D18: =F13 -> 4.561862 | E18: =_xlfn.PERCENTILE.INC(F5:F11,0.75) -> 5.034185 | F18: =B18*C18 -> 15544.073 | G18: =B18*D18 -> 16855.478 | H18: =B18*E18 -> 18600.649 | I18: NTM Revenue (FY2026E projected)
A19: EV / EBITDA - FY1 | B19: 886.7 | C19: =_xlfn.PERCENTILE.INC(G5:G11,0.25) -> 14.153807 | D19: =G13 -> 14.934707 | E19: =_xlfn.PERCENTILE.INC(G5:G11,0.75) -> 18.311642 | F19: =B19*C19 -> 12550.181 | G19: =B19*D19 -> 13242.604 | H19: =B19*E19 -> 16236.933 | I19: Note: EBITDA metric uses FactSet consensus adjusted EBITDA (excl. SBC), consistent with peer group reporting.
A20: EV / EBITDA - FY2 | B20: 1094.1 | C20: =_xlfn.PERCENTILE.INC(H5:H11,0.25) -> 13.04922 | D20: =H13 -> 13.12515 | E20: =_xlfn.PERCENTILE.INC(H5:H11,0.75) -> 14.943535 | F20: =B20*C20 -> 14277.152 | G20: =B20*D20 -> 14360.226 | H20: =B20*E20 -> 16349.722
A21: Implied Enterprise Value Range — Trading Comps (Overall) | F21: =MIN(F18:F20) -> 12550.181 | G21: =AVERAGE(G18:G20) -> 14819.436 | H21: =MAX(H18:H20) -> 18600.649

Sheet Transaction Comps
A2: PRECEDENT TRANSACTION ANALYSIS — SaaS / CRM Sector (2018–2023)
A3: Selected Precedent Transactions
A4: Target | B4: Acquirer | C4: Year | D4: Deal Value ($M) | E4: LTM Revenue ($M) | F4: EV / LTM Revenue | G4: EV / LTM EBITDA | H4: <-- All Target companies were acquired before becoming profitable
A5: Zendesk | B5: Hellman & Friedman | C5: 2022 | D5: 10200 | E5: 1700 | F5: 6 | G5: N/M
A6: Qualtrics | B6: Silver Lake / CPP | C6: 2023 | D6: 12500 | E6: 1800 | F6: 6.9 | G6: N/M
A7: Ping Identity | B7: Thoma Bravo | C7: 2022 | D7: 2800 | E7: 332 | F7: 8.4 | G7: N/M
A8: Avalara | B8: Vista Equity | C8: 2022 | D8: 8400 | E8: 756 | F8: 8.8 | G8: N/M
A9: Coupa Software | B9: Thoma Bravo | C9: 2023 | D9: 8000 | E9: 952 | F9: 8.4 | G9: N/M
E10: Mean | F10: =AVERAGE(F5:F9) -> 7.7 | G10: N/M
E11: Median | F11: =MEDIAN(F5:F9) -> 8.4 | G11: N/M
A14: Valuation Method | B14: Metric Used | C14: Metric ($M) | D14: Multiple Low | E14: Multiple Mid | F14: Multiple High | G14: Implied EV Low ($M) | H14: Implied EV Mid ($M) | I14: Implied EV High ($M)
A15: EV / Revenue — LTM | B15: LTM Revenue (FY2025) | C15: ='HUBS-US-IS'!K9 -> 3131.244 | D15: =_xlfn.PERCENTILE.INC($F$5:$F$9,0.25) -> 6.9 | E15: =$F$11 -> 8.4 | F15: =MAX(F5:F9) -> 8.8 | G15: =$C$15*D15 -> 21605.584 | H15: =$C$15*E15 -> 26302.45 | I15: =$C$15*F15 -> 27554.947
A16: EV / Revenue — NTM | B16: NTM Revenue (FY2026E) | C16: ='HUBS Projection'!B59 -> 3694.8679 | D16: =_xlfn.PERCENTILE.INC($F$5:$F$9,0.25) -> 6.9 | E16: =$F$11 -> 8.4 | F16: =MAX(F5:F9) -> 8.8 | G16: =$C$16*D16 -> 25494.589 | H16: =$C$16*E16 -> 31036.891 | I16: =$C$16*F16 -> 32514.838
F17: Precedent Transactions | G17: =MIN(G15:G16) -> 21605.584 | H17: =AVERAGE(H15:H16) -> 28669.67 | I17: =MAX(I15:I16) -> 32514.838

Sheet CRM Projection
B2: JAN '21 | C2: JAN '22 | D2: JAN '23 | E2: JAN '24 | F2: JAN '25 | G2: JAN '26
A3: Sales | B3: ='CRM-US-IS'!F10 -> 21252 | C3: ='CRM-US-IS'!G10 -> 26492 | D3: ='CRM-US-IS'!H10 -> 31352 | E3: ='CRM-US-IS'!I10 -> 34857 | F3: ='CRM-US-IS'!J10 -> 37895 | G3: ='CRM-US-IS'!K10 -> 41525
A4: Sales Growth YoY | C4: =C3/B3-1 -> 0.24656503 | D4: =D3/C3-1 -> 0.18345161 | E4: =E3/D3-1 -> 0.1117951 | F4: =F3/E3-1 -> 0.087156095 | G4: =G3/F3-1 -> 0.095791001
A5: Average Sales Growth | B5: =AVERAGE(C4:G4) -> 0.14495177 | C5: <-- we see that the sales growth rate is declining very slightly so we will use the schedule below
A7: EBIT | B7: ='CRM-US-IS'!F20 -> 455 | C7: ='CRM-US-IS'!G20 -> 548 | D7: ='CRM-US-IS'!H20 -> 1858 | E7: ='CRM-US-IS'!I20 -> 5999 | F7: ='CRM-US-IS'!J20 -> 7666 | G7: ='CRM-US-IS'!K20 -> 8917
A8: EBIT as % of Sales | C8: =C7/C3 -> 0.02068549 | D8: =D7/D3 -> 0.059262567 | E8: =E7/E3 -> 0.17210316 | F8: =F7/F3 -> 0.20229582 | G8: =G7/G3 -> 0.21473811
A9: Average EBIT | B9: =AVERAGE(C8:G8) -> 0.13381703
A11: Depreciation & Amortization | B11: ='CRM-US-IS'!F13 -> 2846 | C11: ='CRM-US-IS'!G13 -> 3298 | D11: ='CRM-US-IS'!H13 -> 3786 | E11: ='CRM-US-IS'!I13 -> 3959 | F11: ='CRM-US-IS'!J13 -> 3477 | G11: ='CRM-US-IS'!K13 -> 3631
A12: Depreciation & Amortization as % of Sales | C12: =C11/C3 -> 0.12449041 | D12: =D11/D3 -> 0.12075785 | E12: =E11/E3 -> 0.11357833 | F12: =F11/F3 -> 0.091753529 | G12: =G11/G3 -> 0.0874413
A13: Average D&A | B13: =AVERAGE(C12:G12) -> 0.10760428
A15: CAPEX | B15: ='CRM-US-CF'!F23 -> -710 | C15: ='CRM-US-CF'!G23 -> -717 | D15: ='CRM-US-CF'!H23 -> -798 | E15: ='CRM-US-CF'!I23 -> -736 | F15: ='CRM-US-CF'!J23 -> -658 | G15: ='CRM-US-CF'!K23 -> -594
A16: CAPEX as % of Sales | C16: =-C15/C3 -> 0.027064774 | D16: =-D15/D3 -> 0.025452922 | E16: =-E15/E3 -> 0.021114841 | F16: =-F15/F3 -> 0.017363768 | G16: =-G15/G3 -> 0.014304636
A17: Average CAPEX | B17: =AVERAGE(C16:G16) -> 0.021060188
A19: NWC | B19: =(('CRM-US-BS'!F15+'CRM-US-BS'!F19)-('CRM-US-BS'!F46+'CRM-US-BS'!F48))*1000 -> -8150 | C19: =(('CRM-US-BS'!G15+'CRM-US-BS'!G19)-('CRM-US-BS'!G46+'CRM-US-BS'!G48))*1000 -> -10129 | D19: =(('CRM-US-BS'!H15+'CRM-US-BS'!H19)-('CRM-US-BS'!H46+'CRM-US-BS'!H48))*1000 -> -11751 | E19: =(('CRM-US-BS'!I15+'CRM-US-BS'!I19)-('CRM-US-BS'!I46+'CRM-US-BS'!I48))*1000 -> -11767 | F19: =(('CRM-US-BS'!J15+'CRM-US-BS'!J19)-('CRM-US-BS'!J46+'CRM-US-BS'!J48))*1000 -> -13340 | G19: =(('CRM-US-BS'!K15+'CRM-US-BS'!K19)-('CRM-US-BS'!K46+'CRM-US-BS'!K48))*1000 -> -15713
A20: NWC as % of Sale | C20: =C19/C3 -> -0.38234184 | D20: =D19/D3 -> -0.37480862 | E20: =E19/E3 -> -0.33757925 | F20: =F19/F3 -> -0.35202533 | G20: =G19/G3 -> -0.37839856
A21: Average NWC | B21: =AVERAGE(C20:G20) -> -0.36503072
B23: 2026 | C23: 2027 | D23: 2028 | E23: 2029 | F23: 2030 | G23: Perpetuity
A24: Sales growth for the upcoming years assumed | B24: 0.095 | C24: 0.105 | D24: 0.11 | E24: 0.1 | F24: 0.09 | G24: 0.035
A25: EBIT MARGIN for the upcoming years assumed | B25: 0.225 | C25: 0.235 | D25: 0.245 | E25: 0.25 | F25: 0.255
A26: D&A MARGIN for the upcoming years assumed | B26: 0.085 | C26: 0.083 | D26: 0.082 | E26: 0.081 | F26: 0.08
A28: WACC Assumptions
A29: Beta | B29: =Beta!N2 -> 1.2317362
A30: Market Risk Premium | B30: =Assumptions!K14 -> 0.06
A31: 10-year Risk-Free Rate | B31: =Assumptions!K15 -> 0.0439
A32: Cost of Equity | B32: =B31+B29*B30 -> 0.11780417
B34: JAN '21 | C34: JAN '22 | D34: JAN '23 | E34: JAN '24 | F34: JAN '25 | G34: JAN '26
A35: Pretax Income | B35: ='CRM-US-IS'!F35 -> 2561 | C35: ='CRM-US-IS'!G35 -> 1532 | D35: ='CRM-US-IS'!H35 -> 660 | E35: ='CRM-US-IS'!I35 -> 4950 | F35: ='CRM-US-IS'!J35 -> 7438 | G35: ='CRM-US-IS'!K35 -> 9520
A36: Income Tax | B36: ='CRM-US-IS'!F36 -> -1511 | C36: ='CRM-US-IS'!G36 -> 88 | D36: ='CRM-US-IS'!H36 -> 452 | E36: ='CRM-US-IS'!I36 -> 814 | F36: ='CRM-US-IS'!J36 -> 1241 | G36: ='CRM-US-IS'!K36 -> 2063
A37: Effective Tax Rate | B37: =B36/B35 -> -0.5900039 | C37: =C36/C35 -> 0.057441253 | D37: =D36/D35 -> 0.68484848 | E37: =E36/E35 -> 0.16444444 | F37: =F36/F35 -> 0.16684593 | G37: =G36/G35 -> 0.21670168
A38: Average Tax Rate | B38: =AVERAGE(C37:G37) -> 0.25805636
A39: Tax Rate Used | B39: 0.21 | C39: <-- we are using 21% because the average includes outliers
A42: Risk Free Rate | B42: =B31 -> 0.0439
A43: Default Spread | B43: 0.0125
A44: Pre-Tax Cost of Debt | B44: =SUM(B42:B43) -> 0.0564
A45: After-Tax Cost of Debt | B45: =B44*(1-B39) -> 0.044556
A47: Shares Outstanding | B47: ='CRM-US-IS'!K50 -> 956
A48: Price per Share | B48: =Beta!B4 -> 195.18
A49: Market Cap | B49: =B47*B48 -> 186592.08
A50: Total Debt | B50: =('CRM-US-BS'!K45+'CRM-US-BS'!K54)*1000 -> 15262
A52: Weight of Debt | B52: =B50/(B50+B49) -> 0.075609074
A53: Weight of Equity | B53: =B49/(B49+B50) -> 0.92439093
A55: WACC | B55: =B53*B32+B52*B45 -> 0.11226594
B57: 1 | C57: 2 | D57: 3 | E57: 4 | F57: 5
A58: Free Cash Flow Calculation | B58: 2026 | C58: 2027 | D58: 2028 | E58: 2029 | F58: 2030
A59: Revenue | B59: =G3*(1+B24) -> 45469.875 | C59: =B59*(1+C24) -> 50244.212 | D59: =C59*(1+D24) -> 55771.075 | E59: =D59*(1+E24) -> 61348.183 | F59: =E59*(1+F24) -> 66869.519
A60: EBIT | B60: =B59*B25 -> 10230.722 | C60: =C59*C25 -> 11807.39 | D60: =D59*D25 -> 13663.913 | E60: =E59*E25 -> 15337.046 | F60: =F59*F25 -> 17051.727
A61: NOPAT | B61: =B60*(1-$B$39) -> 8082.2703 | C61: =C60*(1-$B$39) -> 9327.8379 | D61: =D60*(1-$B$39) -> 10794.492 | E61: =E60*(1-$B$39) -> 12116.266 | F61: =F60*(1-$B$39) -> 13470.865
A62: D&A | B62: =B59*B26 -> 3864.9394 | C62: =C59*C26 -> 4170.2696 | D62: =D59*D26 -> 4573.2282 | E62: =E59*E26 -> 4969.2028 | F62: =F59*F26 -> 5349.5615
A63: CAPEX | B63: =B59*$B$17 -> 957.60412 | C63: =C59*$B$17 -> 1058.1526 | D63: =D59*$B$17 -> 1174.5493 | E63: =E59*$B$17 -> 1292.0043 | F63: =F59*$B$17 -> 1408.2847
A64: NWC | B64: =B59*$B$21 -> -16597.901 | C64: =C59*$B$21 -> -18340.681 | D64: =D59*$B$21 -> -20358.156 | E64: =E59*$B$21 -> -22393.971 | F64: =F59*$B$21 -> -24409.429
A65: Change in NWC | B65: =B64-G19 -> -884.90125 | C65: =C64-B64 -> -1742.7796 | D65: =D64-C64 -> -2017.4749 | E65: =E64-D64 -> -2035.8156 | F65: =F64-E64 -> -2015.4574
A66: FCF | B66: =B61+B62-B63-B65 -> 11874.507 | C66: =C61+C62-C63-C65 -> 14182.735 | D66: =D61+D62-D63-D65 -> 16210.645 | E66: =E61+E62-E63-E65 -> 17829.28 | F66: =F61+F62-F63-F65 -> 19427.599
A67: PV of FCF | B67: =B66/(1+$B$55)^B57 -> 10675.96 | C67: =C66/(1+$B$55)^C57 -> 11464.172 | D67: =D66/(1+$B$55)^D57 -> 11780.789 | E67: =E66/(1+$B$55)^E57 -> 11649.284 | F67: =F66/(1+$B$55)^F57 -> 11412.372
A68: Total PV of FCF | B68: =SUM(B67:F67) -> 56982.578
A69: Terminal Value | B69: =F66*(1+G24)/(B55-G24) -> 260238.39
A70: PV of Terminal Value | B70: =B69/(1+B55)^F57 -> 152872.08
A71: Enterprise Value | B71: =B70+B68 -> 209854.66

Sheet HUBS Projection
B2: JAN '21 | C2: JAN '22 | D2: JAN '23 | E2: JAN '24 | F2: JAN '25 | G2: JAN '26
A3: Sales | B3: ='HUBS-US-IS'!F9 -> 883.026 | C3: ='HUBS-US-IS'!G9 -> 1300.658 | D3: ='HUBS-US-IS'!H9 -> 1730.969 | E3: ='HUBS-US-IS'!I9 -> 2170.23 | F3: ='HUBS-US-IS'!J9 -> 2627.543 | G3: ='HUBS-US-IS'!K9 -> 3131.244
A4: Sales Growth YoY | C4: =C3/B3-1 -> 0.4729555 | D4: =D3/C3-1 -> 0.33084101 | E4: =E3/D3-1 -> 0.25376595 | F4: =F3/E3-1 -> 0.21072098 | G4: =G3/F3-1 -> 0.19170038
A5: Average Sales Growth | B5: =AVERAGE(C4:G4) -> 0.29199676 | C5: <-- Since this number is too high compared tot the previous 3 years and since the growth is declining we will use a declining rate ranging from 18% down to 13% for the forecasting period
A7: EBIT | B7: ='HUBS-US-IS'!F19 -> -50.828 | C7: ='HUBS-US-IS'!G19 -> -52.607 | D7: ='HUBS-US-IS'!H19 -> -109.101 | E7: ='HUBS-US-IS'!I19 -> -104.086 | F7: ='HUBS-US-IS'!J19 -> -63.612 | G7: ='HUBS-US-IS'!K19 -> 11.393
A8: EBIT as % of Sales | C8: =C7/C3 -> -0.040446451 | D8: =D7/D3 -> -0.063028858 | E8: =E7/E3 -> -0.047960815 | F8: =F7/F3 -> -0.024209689 | G8: =G7/G3 -> 0.00363849
A9: Average EBIT | B9: =AVERAGE(C8:G8) -> -0.034401465 | C9: <-- 2025 is a reflectionefrelc for the EBIT, because of this we are going to use a gradual increase in the %-age. It will range from 5% to 15%. This is similar to the FactSet Consensus.
A11: Depreciation & Amortization | B11: ='HUBS-US-IS'!F12 -> 39.2 | C11: ='HUBS-US-IS'!G12 -> 48.2 | D11: ='HUBS-US-IS'!H12 -> 62.4 | E11: ='HUBS-US-IS'!I12 -> 80.1 | F11: ='HUBS-US-IS'!J12 -> 113.6 | G11: ='HUBS-US-IS'!K12 -> 164.5
A12: Depreciation & Amortization as % of Sales | C12: =C11/C3 -> 0.037058166 | D12: =D11/D3 -> 0.036049172 | E12: =E11/E3 -> 0.03690853 | F12: =F11/F3 -> 0.043234307 | G12: =G11/G3 -> 0.052535031
A13: Average D&A | B13: =AVERAGE(C12:G12) -> 0.041157041
A15: CAPEX | B15: =-'HUBS-US-CF'!F25 -> 58.873 | C15: =-'HUBS-US-CF'!G25 -> 61.865 | D15: =-'HUBS-US-CF'!H25 -> 91.771 | E15: =-'HUBS-US-CF'!I25 -> 100.254 | F15: =-'HUBS-US-CF'!J25 -> 128.806 | G15: =-'HUBS-US-CF'!K25 -> 184.063
A16: CAPEX as % of Sales | C16: =C15/C3 -> 0.047564387 | D16: =D15/D3 -> 0.053017125 | E16: =E15/E3 -> 0.046195104 | F16: =F15/F3 -> 0.049021462 | G16: =G15/G3 -> 0.058782707
A17: Average CAPEX | B17: =AVERAGE(C16:G16) -> 0.050916157
A19: NWC | B19: ='HUBS-US-BS'!F13+'HUBS-US-BS'!F17-'HUBS-US-BS'!F42-'HUBS-US-BS'!F43 -> -246.495 | C19: ='HUBS-US-BS'!G13+'HUBS-US-BS'!G17-'HUBS-US-BS'!G42-'HUBS-US-BS'!G43 -> -375.73 | D19: ='HUBS-US-BS'!H13+'HUBS-US-BS'!H17-'HUBS-US-BS'!H42-'HUBS-US-BS'!H43 -> -454.802 | E19: ='HUBS-US-BS'!I13+'HUBS-US-BS'!I17-'HUBS-US-BS'!I42-'HUBS-US-BS'!I43 -> -522.979 | F19: ='HUBS-US-BS'!J13+'HUBS-US-BS'!J17-'HUBS-US-BS'!J42-'HUBS-US-BS'!J43 -> -667.107 | G19: ='HUBS-US-BS'!K13+'HUBS-US-BS'!K17-'HUBS-US-BS'!K42-'HUBS-US-BS'!K43 -> -908.011
A20: NWC as % of Sale | C20: =C19/C3 -> -0.28887686 | D20: =D19/D3 -> -0.26274416 | E20: =E19/E3 -> -0.24097861 | F20: =F19/F3 -> -0.25389004 | G20: =G19/G3 -> -0.28998411
A21: Average NWC | B21: =AVERAGE(C20:G20) -> -0.26729476
B23: 2026 | C23: 2027 | D23: 2028 | E23: 2029 | F23: 2030 | G23: Perpetuity
A24: Sales growth for the upcoming years assumed | B24: 0.18 | C24: 0.16 | D24: 0.15 | E24: 0.14 | F24: 0.13 | G24: 0.035
A25: EBIT Margins for the upcoming years assumed | B25: 0.05 | C25: 0.08 | D25: 0.11 | E25: 0.13 | F25: 0.15 | G25: =F25 -> 0.15
A28: WACC Assumptions
A29: Beta | B29: =Beta!N3 -> 1.4171699
A30: Market Risk Premium | B30: =Assumptions!B14 -> 0.06
A31: 10-year Risk-Free Rate | B31: =Assumptions!B15 -> 0.0439
A32: Cost of Equity | B32: =B31+B29*B30 -> 0.12893019
B34: DEC '20 | C34: DEC '21 | D34: DEC '22 | E34: DEC '23 | F34: DEC '24 | G34: DEC '25
A35: Pretax Income | B35: ='HUBS-US-IS'!F34 -> -80.815 | C35: ='HUBS-US-IS'!G34 -> -73.818 | D35: ='HUBS-US-IS'!H34 -> -104.692 | E35: ='HUBS-US-IS'!I34 -> -150.575 | F35: ='HUBS-US-IS'!J34 -> 28.677 | G35: ='HUBS-US-IS'!K34 -> 69.463
A36: Income Tax | B36: ='HUBS-US-IS'!F35 -> 4.216 | C36: ='HUBS-US-IS'!G35 -> 4.019 | D36: ='HUBS-US-IS'!H35 -> 8.057 | E36: ='HUBS-US-IS'!I35 -> 13.935 | F36: ='HUBS-US-IS'!J35 -> 24.049 | G36: ='HUBS-US-IS'!K35 -> 23.552
A37: Effective Tax Rate | B37: =B36/B35 -> -0.052168533 | C37: =C36/C35 -> -0.054444715 | D37: =D36/D35 -> -0.07695908 | E37: =E36/E35 -> -0.092545243 | F37: =F36/F35 -> 0.83861631 | G37: =G36/G35 -> 0.3390582
A38: Average Tax Rate | B38: =AVERAGE(E37:G37) -> 0.36170976
A39: Tax Rate Used | B39: 0.25 | C39: <-- We are using 25% because HUBS just became profitable
C40: and we are using a normalized and commonly used number
A42: Risk Free Rate | B42: =B31 -> 0.0439
A43: Default Spread (near-zero debt) | B43: 0.0063 | C43: <-- Damodaran Table
A44: Pre-Tax Cost of Debt | B44: =SUM(B42:B43) -> 0.0502
A45: After-Tax Cost of Debt | B45: =B44*(1-B39) -> 0.03765
A47: Shares Outstanding | B47: 52.74
A48: Price per Share | B48: =Beta!F4 -> 262.06
A49: Market Cap | B49: =B48*B47 -> 13821.044 | C49: <-- add nontradable shares
A50: Total Debt | B50: ='HUBS-US-BS'!K41+'HUBS-US-BS'!K49 -> 39.703
A52: Weight of Debt | B52: =B50/(B50+B49) -> 0.0028644199
A53: Weight of Equity | B53: =B49/(B49+B50) -> 0.99713558
A55: WACC | B55: =B53*B32+B52*B45 -> 0.12866873
B57: 1 | C57: 2 | D57: 3 | E57: 4 | F57: 5
A58: Free Cash Flow Calculation | B58: 2026 | C58: 2027 | D58: 2028 | E58: 2029 | F58: 2030
A59: Revenue | B59: =G3*(1+B24) -> 3694.8679 | C59: =B59*(1+C24) -> 4286.0468 | D59: =C59*(1+D24) -> 4928.9538 | E59: =D59*(1+E24) -> 5619.0073 | F59: =E59*(1+F24) -> 6349.4783
A60: EBIT | B60: =B59*B25 -> 184.7434 | C60: =C59*C25 -> 342.88374 | D60: =D59*D25 -> 542.18492 | E60: =E59*E25 -> 730.47095 | F60: =F59*F25 -> 952.42174
A61: NOPAT | B61: =B60*(1-$B$39) -> 138.55755 | C61: =C60*(1-$B$39) -> 257.16281 | D61: =D60*(1-$B$39) -> 406.63869 | E61: =E60*(1-$B$39) -> 547.85322 | F61: =F60*(1-$B$39) -> 714.31631
A62: D&A | B62: =B59*$B$13 -> 152.06983 | C62: =C59*$B$13 -> 176.401 | D62: =D59*$B$13 -> 202.86116 | E62: =E59*$B$13 -> 231.26172 | F62: =F59*$B$13 -> 261.32574
A63: CAPEX | B63: =B59*$B$17 -> 188.12848 | C63: =C59*$B$17 -> 218.22903 | D63: =D59*$B$17 -> 250.96339 | E63: =E59*$B$17 -> 286.09826 | F63: =F59*$B$17 -> 323.29103
A64: NWC | B64: =B59*$B$21 -> -987.61882 | C64: =C59*$B$21 -> -1145.6378 | D64: =D59*$B$21 -> -1317.4835 | E64: =E59*$B$21 -> -1501.9312 | F64: =F59*$B$21 -> -1697.1822
A65: Change in NWC | B65: =B64-G19 -> -79.607818 | C65: =C64-B64 -> -158.01901 | D65: =D64-C64 -> -171.84567 | E65: =E64-D64 -> -184.44769 | F65: =F64-E64 -> -195.25106
A66: FCF | B66: =B61+B62-B63-B65 -> 182.10672 | C66: =C61+C62-C63-C65 -> 373.35379 | D66: =D61+D62-D63-D65 -> 530.38213 | E66: =E61+E62-E63-E65 -> 677.46436 | F66: =F61+F62-F63-F65 -> 847.60207
A67: PV of FCF | B67: =B66/(1+$B$55)^B57 -> 161.34648 | C67: =C66/(1+$B$55)^C57 -> 293.08094 | D67: =D66/(1+$B$55)^D57 -> 368.88365 | E67: =E66/(1+$B$55)^E57 -> 417.4654 | F67: =F66/(1+$B$55)^F57 -> 462.76398
A68: Total PV of FCF | B68: =SUM(B67:F67) -> 1703.5405
A69: Terminal Value | B69: =F66*(1+G24)/(B55-G24) -> 9365.6461
A70: PV of Terminal Value | B70: =B69/(1+B55)^F57 -> 5113.3472
A71: Enterprise Value | B71: =B70+B68 -> 6816.8877
C74: Growth Rate
B75: =B71 -> 6816.8877 | C75: 0.025 | D75: 0.03 | E75: 0.035 | F75: 0.04 | G75: 0.045
B76: 0.1187 | C76: 7048.1006 | D76: 7373.6705 | E76: 7738.1376 | F76: 8148.9157 | G76: 8615.4303
B77: 0.12866873 | C77: 6279.0098 | D77: 6534.3204 | E77: 6816.8877 | F77: 7131.3227 | G77: 7483.3387
A78: WACC | B78: 0.1387 | C78: 5644.019 | D78: 5847.9742 | E78: 6071.5971 | F78: 6317.8769 | G78: 6590.4406
B79: 0.1487 | C79: 5115.9633 | D79: 5281.7368 | E79: 5462.0902 | F79: 5659.0355 | G79: 5874.9726
B80: 0.1587 | C80: 4669.0622 | D80: 4805.6991 | E80: 4953.3819 | F80: 5113.5063 | G80: 5287.7138

Sheet Beta
A2: Price History: CRM-US | E2: Price History: HUBS-US | I2: Price History: VOO-US | M2: CRM Beta | N2: =SLOPE(C4:C77,K4:K77) -> 1.2317362 | P2: Methodology: 5-year monthly returns regressed vs. VOO (S&P 500 ETF).
A3: Date | B3: Price | C3: Return | E3: Date | F3: Price | G3: Return | I3: Date | J3: Price | K3: Return | M3: HUBS Beta | N3: =SLOPE(G4:G77,K4:K77) -> 1.4171699 | P3: Cross-referenced with Yahoo Finance reported betas as of March 2026.
A4: 46104 | B4: 195.18 | C4: =B4/B5-1 -> 0.0020021562 | E4: 46104 | F4: 262.06 | G4: =F4/F5-1 -> -0.0092624097 | I4: 46104 | J4: 604.43 | K4: =J4/J5-1 -> -0.042168484
A5: 46080 | B5: 194.79 | C5: =B5/B6-1 -> -0.082434406 | E5: 46080 | F5: 264.51 | G5: =F5/F6-1 -> -0.055321429 | I5: 46080 | J5: 631.04 | K5: =J5/J6-1 -> -0.0081418377
A6: 46052 | B6: 212.29 | C6: =B6/B7-1 -> -0.1986335 | E6: 46052 | F6: 280 | G6: =F6/F7-1 -> -0.30226763 | I6: 46052 | J6: 636.22 | K6: =J6/J7-1 -> 0.014494602
A7: 46022 | B7: 264.91 | C7: =B7/B8-1 -> 0.14908476 | E7: 46022 | F7: 401.3 | G7: =F7/F8-1 -> 0.092507895 | I7: 46022 | J7: 627.13 | K7: =J7/J8-1 -> -0.0020368867
A8: 45989 | B8: 230.54 | C8: =B8/B9-1 -> -0.11470374 | E8: 45989 | F8: 367.32 | G8: =F8/F9-1 -> -0.25329322 | I8: 45989 | J8: 628.41 | K8: =J8/J9-1 -> 0.0021848686
A9: 45961 | B9: 260.41 | C9: =B9/B10-1 -> 0.098776371 | E9: 45961 | F9: 491.92 | G9: =F9/F10-1 -> 0.051560496 | I9: 45961 | J9: 627.04 | K9: =J9/J10-1 -> 0.023939384
A10: 45930 | B10: 237 | C10: =B10/B11-1 -> -0.075121951 | E10: 45930 | F10: 467.8 | G10: =F10/F11-1 -> -0.03181075 | I10: 45930 | J10: 612.38 | K10: =J10/J11-1 -> 0.032541984
A11: 45898 | B11: 256.25 | C11: =B11/B12-1 -> -0.0080517168 | E11: 45898 | F11: 483.17 | G11: =F11/F12-1 -> -0.070201097 | I11: 45898 | J11: 593.08 | K11: =J11/J12-1 -> 0.0207566
A12: 45869 | B12: 258.33 | C12: =B12/B13-1 -> -0.05266053 | E12: 45869 | F12: 519.65 | G12: =F12/F13-1 -> -0.066435514 | I12: 45869 | J12: 581.02 | K12: =J12/J13-1 -> 0.02286851
A13: 45838 | B13: 272.69 | C13: =B13/B14-1 -> 0.027584128 | E13: 45838 | F13: 556.63 | G13: =F13/F14-1 -> -0.05639939 | I13: 45838 | J13: 568.03 | K13: =J13/J14-1 -> 0.048490106
A14: 45807 | B14: 265.37 | C14: =B14/B15-1 -> -0.012429757 | E14: 45807 | F14: 589.9 | G14: =F14/F15-1 -> -0.035322976 | I14: 45807 | J14: 541.76 | K14: =J14/J15-1 -> 0.062816338
A15: 45777 | B15: 268.71 | C15: =B15/B16-1 -> 0.0013042182 | E15: 45777 | F15: 611.5 | G15: =F15/F16-1 -> 0.070384568 | I15: 45777 | J15: 509.74 | K15: =J15/J16-1 -> -0.0081142613
... A65: 44253 | B65: 216.5 | C65: =B65/B66-1 -> -0.040166696 | E65: 44253 | F65: 515 | G65: =F65/F66-1 -> 0.3836647 | I65: 44253 | J65: 349.59 | K65: =J65/J66-1 -> 0.027661826
A66: 44225 | B66: 225.56 | E66: 44225 | F66: 372.2 | I66: 44225 | J66: 340.18

Sheet Raw Comps
A2: Selected Financials
D3: Sales ($) | F3: EBITDA | J3: EBIT | N3: FCF
A4: Company | C4: Fiscal | G4: Margin | I4: Margin | K4: Margin | M4: Margin
A5: Name | B5: Ticker | C5: Period | D5: FY1 | E5: FY2 | F5: FY1 | G5: FY1 (%) | H5: FY2 | I5: FY2 (%) | J5: FY1 | K5: FY1 (%) | L5: FY2 | M5: FY2 (%) | N5: FY1 | O5: FY2
A6: Okta A | B6: OKTA-US | C6: 01/2026 | D6: 3183.3779 | E6: 3483.6277 | F6: 838.48767 | G6: 26.339558 | H6: 961.44739 | I6: 27.599028 | J6: 810.73657 | K6: 25.467808 | L6: 921.99188 | M6: 26.466429 | N6: 872.55249 | O6: 997.32831
A7: Roku A | B7: ROKU-US | C7: 12/2025 | D7: 5502.4629 | E7: 6159.3965 | F7: 641.76233 | G7: 11.663183 | H7: 844.09369 | I7: 13.704163 | J7: 244.44041 | K7: 4.442382 | L7: 455.75693 | M7: 7.399376 | N7: 743.54291 | O7: 908.64887
A8: Tyler Technologies | B8: TYL-US | C8: 12/2025 | D8: 2531.1392 | E8: 2777.762 | F8: 738.33356 | G8: 29.17001 | H8: 842.93579 | I8: 30.34586 | J8: 687.78314 | K8: 27.172869 | L8: 778.94348 | M8: 28.042126 | N8: 680.40674 | O8: 773.43127
A9: Gen Digital | B9: GEN-US | C9: 01/02/2026 | D9: 4960.8027 | E9: 5240.9624 | F9: 2481.2671 | G9: 50.017452 | H9: 2634.9973 | I9: 50.276978 | J9: 2540.217 | K9: 51.205765 | L9: 2697.2747 | M9: 51.465256 | N9: 1473.4334 | O9: 1494.7
A10: Jack Henry & Associates | B10: JKHY-US | C10: 12/31/2025 | D10: 2519.6321 | E10: 2677.5244 | F10: 811.12012 | G10: 32.192005 | H10: 869.67798 | I10: 32.480675 | J10: 615.13654 | K10: 24.413746 | L10: 654.98981 | M10: 24.462515 | N10: 458.95776 | O10: 470.10559
A11: Dynatrace | B11: DT-US | C11: 12/31/2025 | D11: 2007.6473 | E11: 2304.9592 | F11: 607.396 | G11: 30.254116 | H11: 711.89819 | I11: 30.8855 | J11: 585.9447 | K11: 29.185638 | L11: 682.78778 | M11: 29.622555 | N11: 522.08679 | O11: 609.25366
A12: Trimble | B12: TRMB-US | C12: 12/2025 | D12: 3866.2544 | E12: 4182.0425 | F12: 1149.6221 | G12: 29.734776 | H12: 1251.7284 | I12: 29.93103 | J12: 1094.9644 | K12: 28.321064 | L12: 1223.3566 | M12: 29.252609 | N12: 840.58716 | O12: 955.01471
A13: Average | G13: 24.39638 | I13: 26.08772 | K13: 20.642271 | M13: 22.285069 | N13: 645.49836 | O13: 732.001
A14: Median | G14: 27.754784 | I14: 28.765029 | K14: 24.940777 | M14: 25.464472 | N14: 711.30277 | O14: 830.99747
A16: Valuation
E17: Market Data ($) | I17: Valuation (x) | K17: EV/EBITDA (x) | M17: P/E (x) | O17: P/FCF (x)
A18: Company | C18: Fiscal | E18: Price | F18: Enterprise | G18: Market | H18: Net | I18: Price/ | J18: EV/ | Q18: FCF | R18: Div
A19: Name | B19: Ticker | C19: Period | D19: Price | E19: Target | F19: Value | G19: Value | H19: Debt | I19: Sales | J19: Sales | K19: FY1 | L19: FY2 | M19: FY1 | N19: FY2 | O19: FY1 | P19: FY2 | Q19: Yield (%) | R19: Yield (%)
A20: Okta A | B20: OKTA-US | C20: 01/2026 | D20: 80.190002 | E20: 101.28205 | F20: 12522.567 | G20: 14726.567 | H20: -2132 | I20: 4.925408 | J20: 4.29002 | K20: 14.934706 | L20: 13.024703 | M20: 21.156017 | N20: 19.015495 | O20: 17.025478 | P20: 14.866519 | Q20: 5.776943 | R20: 0
A21: Roku A | B21: ROKU-US | C21: 12/2025 | D21: 97.660004 | E21: 128.62962 | F21: 12774.137 | G21: 15091.418 | H21: -1793.957 | I21: 3.111101 | J21: 2.696529 | K21: 19.904779 | L21: 15.133553 | M21: 45.317909 | N21: 30.166357 | O21: 19.644255 | P21: 15.957518 | Q21: 1.91534 | R21: 0
A22: Tyler Technologies | B22: TYL-US | C22: 12/2025 | D22: 338.03 | E22: 440.64999 | F22: 14273.045 | G22: 14770.582 | H22: -454.592 | I22: 6.349748 | J22: 6.119624 | K22: 19.331432 | L22: 16.932541 | M22: 26.965561 | N22: 23.832756 | O22: 20.82748 | P22: 18.727425 | Q22: 3.205518 | R22: 0
A23: Gen Digital | B23: GEN-US | C23: 01/02/2026 | D23: 18.889999 | E23: 32.666668 | F23: 19493.449 | G23: 11705.449 | H23: 7788 | I23: 2.469647 | J23: 4.123852 | K23: 7.856248 | L23: 7.397901 | M23: 7.415899 | N23: 6.639049 | O23: 6.944853 | P23: 7.773662 | Q23: 7.312495 | R23: 2.646903
A24: Jack Henry & Associates | B24: JKHY-US | C24: 12/31/2025 | D24: 157.48 | E24: 199.21428 | F24: 11414.654 | G24: 11422.87 | H24: 40.281 | I24: 4.627087 | J24: 4.631572 | K24: 14.072705 | L24: 13.125149 | M24: 23.499084 | N24: 21.907619 | O24: 25.4205 | P24: 23.141808 | Q24: 4.469019 | R24: 1.549403
A25: Dynatrace | B25: DT-US | C25: 12/31/2025 | D25: 37.689999 | E25: 49.580647 | F25: 10503.002 | G25: 11691.316 | H25: -1102.495 | I25: 5.916389 | J25: 5.436798 | K25: 17.291853 | L25: 14.753517 | M25: 22.390848 | N25: 19.727514 | O25: 21.760969 | P25: 18.639959 | Q25: 3.027021 | R25: 0
A26: Trimble | B26: TRMB-US | C26: 12/2025 | D26: 65.120003 | E26: 90.583336 | F26: 16364.767 | G26: 15557.367 | H26: 1316.7 | I26: 4.383932 | J26: 4.561862 | K26: 14.23491 | L26: 13.073736 | M26: 18.349924 | N26: 16.106863 | O26: 17.86557 | P26: 15.635055 | Q26: 1.907839 | R26: 0
A27: Average | I27: =AVERAGE(I20:I26) -> 4.5404731 | J27: =AVERAGE(J20:J26) -> 4.5514653 | K27: =AVERAGE(K20:K26) -> 15.375233 | L27: =AVERAGE(L20:L26) -> 13.348729 | M27: =AVERAGE(M20:M26) -> 23.585035 | N27: =AVERAGE(N20:N26) -> 19.62795 | O27: =AVERAGE(O20:O26) -> 18.498444 | P27: =AVERAGE(P20:P26) -> 16.391707 | ... R27: =AVERAGE(R20:R26) -> 0.59947229
A28: Median | I28: =MEDIAN(I20:I26) -> 4.627087 | J28: =MEDIAN(J20:J26) -> 4.561862 | K28: =MEDIAN(K20:K26) -> 14.934706 | L28: =MEDIAN(L20:L26) -> 13.125149 | M28: =MEDIAN(M20:M26) -> 22.390848 | N28: =MEDIAN(N20:N26) -> 19.727514 | O28: =MEDIAN(O20:O26) -> 19.644255 | P28: =MEDIAN(P20:P26) -> 15.957518 | ... R28: =MEDIAN(R20:R26) -> 0
A29: Margins
D30: Gross Margin (%) | F30: EBITDA Margin (%) | H30: EBIT Margin (%) | J30: Pretax Margin (%) | L30: Net Margin (%)
A31: Company | C31: Fiscal
A32: Name | B32: Ticker | C32: Period | D32: Actual | E32: NTM | F32: Actual | G32: NTM | H32: Actual | I32: NTM | J32: Actual | K32: NTM | L32: Actual | M32: NTM
A33: Okta | B33: OKTA-US | C33: 01/2026 | D33: 77.355259 | E33: 82.101524 | F33: 8.530319 | G33: 26.569981 | H33: 5.241521 | I33: 25.650507 | J33: 8.735868 | K33: 28.238266 | L33: 8.050702 | M33: 22.19825
A34: Roku | B34: ROKU-US | C34: 12/2025 | D34: 43.789616 | E34: 44.592304 | F34: 6.845764 | G34: 12.228115 | H34: -0.05404 | I34: 5.260861 | J34: 1.98212 | K34: 6.740084 | L34: 1.865238 | M34: 6.301614
A35: Tyler Technologies | B35: TYL-US | C35: 12/2025 | D35: 44.045079 | E35: 50.762264 | F35: 21.675227 | G35: 29.490837 | H35: 15.3355 | I35: 27.410046 | J35: 16.735039 | K35: 28.401804 | L35: 13.531603 | M35: 14.84304
A36: Gen Digital | B36: GEN-US | C36: 01/02/2026 | D36: 74.44468 | E36: 81.856918 | F36: 47.450814 | G36: 50.288509 | H36: 37.338693 | I36: 51.463135 | J36: 23.88407 | K36: 40.3918 | L36: 12.756505 | M36: 33.394997
A37: Jack Henry & Associates | B37: JKHY-US | C37: 12/31/2025 | D37: 43.842459 | E37: 42.804985 | F37: 34.294557 | G37: 32.414238 | H37: 25.873077 | I37: 24.45129 | J37: 26.632572 | K37: 25.099495 | L37: 20.586716 | M37: 19.110092
A38: Dynatrace | B38: DT-US | C38: 12/31/2025 | D38: 81.574419 | E38: 84.160515 | F38: 14.261511 | G38: 30.863655 | H38: 12.990699 | I38: 29.629278 | J38: 15.977029 | K38: 31.517277 | L38: 9.553451 | M38: 25.444281
A39: Trimble | B39: TRMB-US | C39: 12/2025 | D39: 66.097065 | E39: 72.232635 | F39: 23.145541 | G39: 29.787762 | H39: 17.573105 | I39: 28.572569 | J39: 14.200095 | K39: 26.88764 | L39: 11.819474 | M39: 22.169373
A40: Average | D40: =AVERAGE(D33:D39) -> 61.592654 | E40: =AVERAGE(E33:E39) -> 65.501592 | F40: =AVERAGE(F33:F39) -> 22.314819 | G40: =AVERAGE(G33:G39) -> 30.234728 | H40: =AVERAGE(H33:H39) -> 16.328365 | I40: =AVERAGE(I33:I39) -> 27.491098 | J40: =AVERAGE(J33:J39) -> 15.449542 | K40: =AVERAGE(K33:K39) -> 26.753767 | ... M40: =AVERAGE(M33:M39) -> 20.494521
A41: Median | D41: =MEDIAN(D33:D39) -> 66.097065 | E41: =MEDIAN(E33:E39) -> 72.232635 | F41: =MEDIAN(F33:F39) -> 21.675227 | G41: =MEDIAN(G33:G39) -> 29.787762 | H41: =MEDIAN(H33:H39) -> 15.3355 | I41: =MEDIAN(I33:I39) -> 27.410046 | J41: =MEDIAN(J33:J39) -> 15.977029 | K41: =MEDIAN(K33:K39) -> 28.238266 | ... M41: =MEDIAN(M33:M39) -> 22.169373

Sheet CRM-US-BS
A2: Salesforce, Inc. (CRM)
A5: Salesforce, Inc.
A6: CRM 79466L302 2310525 NYSE Common stock
A7: Source: FactSet Fundamentals
B8: JAN '17 | C8: JAN '18 | D8: JAN '19 | E8: JAN '20 | F8: JAN '21 | G8: JAN '22 | H8: JAN '23 | I8: JAN '24 | J8: JAN '25 | K8: JAN '26
C9: Restate
A10: Assets
A11: Cash & Short-Term Investments | B11: 2.208887 | C11: 4.521 | D11: 4.342 | E11: 7.947 | F11: 11.966 | G11: 10.537 | H11: 12.508 | I11: 14.194 | J11: 14.032 | K11: 9.565
A12: Cash Only | B12: 1.606549 | C12: 2.543 | D12: 2.669 | E12: 4.145 | F12: 5.052 | G12: 4.293 | H12: 5.139 | I12: 7.135 | J12: 7.15 | K12: 5.934
A13: Total Short Term Investments | B13: 0.602338 | C13: 1.978 | D13: 1.673 | E13: 3.802 | F13: 6.914 | G13: 6.244 | H13: 7.369 | I13: 7.059 | J13: 6.882 | K13: 3.631
A14: Short-Term Receivables | B14: 3.23082 | C14: 3.921 | D14: 4.924 | E14: 6.623 | F14: 8.263 | G14: 10.326 | H14: 11.403 | I14: 11.414 | J14: 11.945 | K14: 14.339
A15: Accounts Receivables, Net | B15: 3.196643 | C15: 3.921 | D15: 4.924 | E15: 6.623 | F15: 8.263 | G15: 10.326 | H15: 11.403 | I15: 11.414 | J15: 11.945 | K15: 14.339
A16: Accounts Receivables, Gross | B16: 3.208682 | C16: 3.942 | D16: 4.946 | E16: 6.646 | F16: 8.263 | G16: 10.326 | H16: 11.403 | I16: 11.414 | J16: 11.945 | K16: 14.339
A17: Bad Debt/Doubtful Accounts | B17: -0.012039 | C17: -0.021 | D17: -0.022 | E17: -0.023
A18: Other Receivables | B18: 0.034177 | C18: 0 | D18: 0 | E18: 0 | F18: 0 | G18: 0 | H18: 0 | I18: 0 | J18: 0 | K18: 0
A19: Other Current Assets | B19: 0.24535 | C19: 0.471 | D19: 0.629 | E19: 0.467 | F19: 0.514 | G19: 0.533 | H19: 0.708 | I19: 1.561 | J19: 1.779 | K19: 2.243
A20: Prepaid Expenses | B20: 0.026932
A21: Miscellaneous Current Assets | B21: 0.218418 | C21: 0.471 | D21: 0.629 | E21: 0.467 | F21: 0.514 | G21: 0.533 | H21: 0.708 | I21: 1.561 | J21: 1.779 | K21: 2.243
A22: Total Current Assets | B22: 5.685057 | C22: 8.913 | D22: 9.895 | E22: 15.037 | F22: 20.743 | G22: 21.396 | H22: 24.619 | I22: 27.169 | J22: 27.756 | K22: 26.147
A23: Net Property, Plant & Equipment | B23: 1.787534 | C23: 1.947 | D23: 2.051 | E23: 5.415 | F23: 5.663 | G23: 5.695 | H23: 6.592 | I23: 6.055 | J23: 5.393 | K23: 5.123
A24: Property, Plant & Equipment - Gross | B24: 2.985884 | C24: 3.403 | D24: 3.834 | E24: 7.216 | F24: 7.618 | G24: 8.096 | H24: 9.294 | I24: 9.207 | J24: 9.075 | K24: 8.826
A25: Buildings | B25: 0.621377 | C25: 0.626 | D25: 0.629 | E25: 0.777 | F25: 0.485 | G25: 0.487 | H25: 0.489 | I25: 0.49 | J25: 0.492 | K25: 0.5
A26: Land & Improvements | B26: 0.183888 | C26: 0.184 | D26: 0.184 | E26: 0.184 | F26: 0.293 | G26: 0.293 | H26: 0.293 | I26: 0.293 | J26: 0.293 | K26: 0.357
A27: Leases | B27: 0.729 | C27: 0.709 | D27: 0.671
A28: Computer Software and Equipment | B28: 0.711986 | C28: 0.92 | D28: 1.064 | E28: 1.608 | F28: 1.901 | G28: 2.543 | H28: 3.556 | I28: 4.209 | J28: 4.345 | K28: 4.104
A29: Other Property, Plant & Equipment | B29: 0.739633 | C29: 0.964 | D29: 1.286 | E29: 1.607 | F29: 1.735 | G29: 1.893 | H29: 2.066 | I29: 1.849 | J29: 1.788 | K29: 1.862
A30: Operating Lease Right-of-Use Assets | E30: 3.04 | F30: 3.204 | G30: 2.88 | H30: 2.89 | I30: 2.366 | J30: 2.157 | K30: 2.003
A31: Accumulated Depreciation | B31: 1.19835 | C31: 1.456 | D31: 1.783 | E31: 1.801 | F31: 1.955 | G31: 2.401 | H31: 2.702 | I31: 3.152 | J31: 3.682 | K31: 3.703
A32: Total Long-Term Investments | B32: 0.848686 | C32: 0.836 | D32: 1.423 | E32: 2.056 | F32: 3.951 | G32: 4.784 | H32: 4.672 | I32: 4.848 | J32: 5.576 | K32: 7.591
A33: Other Long-Term Investments | B33: 0.566953 | C33: 0.677 | D33: 1.302 | E33: 1.963 | F33: 3.909 | G33: 4.784 | H33: 4.672 | I33: 4.848 | J33: 4.852 | K33: 7.591
A34: Long-Term Note Receivable | B34: 0.281733 | C34: 0.159 | D34: 0.121 | E34: 0.093 | F34: 0.042 | J34: 0.724
A35: Intangible Assets | B35: 8.558104 | C35: 8.287 | D35: 14.926 | E35: 29.858 | F35: 30.432 | G35: 56.915 | H35: 55.693 | I35: 53.898 | J35: 55.711 | K35: 64.756
A36: Goodwill | B36: 7.263846 | C36: 7.314 | D36: 12.851 | E36: 25.134 | F36: 26.318 | G36: 47.937 | H36: 48.568 | I36: 48.62 | J36: 51.283 | K36: 57.941
A37: Other Intangible Assets | B37: 1.294258 | C37: 0.973 | D37: 2.075 | E37: 4.724 | F37: 4.114 | G37: 8.978 | H37: 7.125 | I37: 5.278 | J37: 4.428 | K37: 6.815
A38: Deferred Tax Assets | B38: 0.028939 | G38: 5.251 | H38: 5.438 | I38: 5.386 | J38: 5.813 | K38: 5.204
A39: Other Assets | B39: 0.6766 | C39: 2.001 | D39: 2.442 | E39: 2.76 | F39: 5.512 | G39: 5.137 | H39: 5.569 | I39: 5.45 | J39: 5.003 | K39: 6.628
A40: Deferred Charges | B40: 0.539619 | C40: 1.776 | D40: 2.02 | E40: 2.274 | F40: 2.861 | G40: 3.796 | H40: 4.473 | I40: 4.42 | J40: 4.446 | K40: 5.06
A41: Tangible Other Assets | B41: 0.136984 | C41: 0.225 | D41: 0.422 | E41: 0.486 | F41: 2.651 | G41: 1.341 | H41: 1.096 | I41: 1.03 | J41: 0.557 | K41: 1.568
A42: Total Assets | B42: 17.584923 | C42: 21.984 | D42: 30.737 | E42: 55.126 | F42: 66.301 | G42: 99.178 | H42: 102.583 | I42: 102.806 | J42: 105.252 | K42: 115.449
A43: Liabilities & Shareholders' Equity
A44: Current
A45: ST Debt & Curr. Portion LT Debt | B45: 0.019594 | C45: 1.025 | D45: 0.203 | E45: 0.803 | F45: 0.801 | G45: 0.8 | H45: 2.029 | I45: 1.889 | J45: 0.916 | K45: 4.823
A46: Accounts Payable | B46: 0.115257 | C46: 0.076 | D46: 0.165 | E46: 1.856 | F46: 2.62 | G46: 2.96 | H46: 3.886 | I46: 3.239 | J46: 3.521 | K46: 4.678
A47: Income Tax Payable | B47: 0.239699
A48: Other Current Liabilities | B48: 6.883803 | C48: 8.966 | D48: 10.887 | E48: 12.186 | F48: 14.307 | G48: 18.028 | H48: 19.976 | I48: 21.503 | J48: 23.543 | K48: 27.617
A49: Accrued Payroll | B49: 0.73039 | C49: 1.001 | D49: 1.167 | E49: 1.5 | F49: 1.7 | G49: 2.4 | H49: 2.6 | I49: 2.5 | J49: 2.8 | K49: 3.3
A50: Miscellaneous Current Liabilities | B50: 6.153413 | C50: 7.965 | D50: 9.72 | E50: 10.686 | F50: 12.607 | G50: 15.628 | H50: 17.376 | I50: 19.003 | J50: 20.743 | K50: 24.317
A51: Total Current Liabilities | B51: 7.258353 | C51: 10.067 | D51: 11.255 | E51: 14.845 | F51: 17.728 | G51: 21.788 | H51: 25.891 | I51: 26.631 | J51: 27.98 | K51: 37.118
A52: Long-Term
A53: Long-Term Debt | B53: 2.689952 | C53: 0.695 | D53: 3.173 | E53: 5.45 | F53: 5.608 | G53: 13.566 | H53: 12.85 | I53: 11.673 | J53: 11.154 | K53: 12.888
A54: Long-Term Debt excl Lease Obligations | B54: 2.008391 | C54: 0.695 | D54: 3.173 | E54: 2.673 | F54: 2.673 | G54: 10.592 | H54: 9.419 | I54: 8.427 | J54: 8.433 | K54: 10.439
A55: Capital and Operating Lease Obligations | B55: 0.681561 | C55: 0 | D55: 0 | E55: 2.777 | F55: 2.935 | G55: 2.974 | H55: 3.431 | I55: 3.246 | J55: 2.721 | K55: 2.449
A56: Deferred Tax Liabilities | B56: 0.099378 | G56: 3.969 | H56: 3.734 | I56: 2.983 | J56: 2.324 | K56: 3.144
A57: Other Liabilities | B57: 0.03711 | C57: 0.846 | D57: 0.704 | E57: 0.946 | F57: 1.472 | G57: 1.724 | H57: 1.749 | I57: 1.873 | J57: 2.621 | K57: 3.157
A58: Other Liabilities (excl. Deferred Income) | B58: 0 | C58: 0.846 | D58: 0.704 | E58: 0.946 | F58: 1.472 | G58: 1.724 | H58: 1.749 | I58: 1.873 | J58: 2.621 | K58: 3.157
A59: Deferred Income | B59: 0.037113
A60: Total Liabilities | B60: 10.084796 | C60: 11.608 | D60: 15.132 | E60: 21.241 | F60: 24.808 | G60: 41.047 | H60: 44.224 | I60: 43.16 | J60: 44.079 | K60: 56.307
A61: Equity
A62: Common Equity | B62: 7.500127 | C62: 10.376 | D62: 15.605 | E62: 33.885 | F62: 41.493 | G62: 58.131 | H62: 58.359 | I62: 59.646 | J62: 61.173 | K62: 59.142
A63: Common Stock Par/Carry Value | B63: 0.000708 | C63: 0.001 | D63: 0.001 | E63: 0.001 | F63: 0.001 | G63: 0.001 | H63: 0.001 | I63: 0.001 | J63: 0.001 | K63: 0.001
A64: Additional Paid-In Capital/Capital Surplus | B64: 8.04017 | C64: 9.752 | D64: 13.927 | E64: 32.116 | F64: 35.601 | G64: 50.919 | H64: 55.047 | I64: 59.841 | J64: 64.576 | K64: 68.835
A65: Retained Earnings | B65: -0.46491 | C65: 0.635 | D65: 1.735 | E65: 1.861 | F65: 5.933 | G65: 7.377 | H65: 7.585 | I65: 11.721 | J65: 16.369 | K65: 22.221
A66: Other Appropriated Reserves | B66: -0.075841 | C66: -0.012 | D66: -0.058 | E66: -0.093 | F66: -0.042 | G66: -0.166 | H66: -0.274 | I66: -0.225 | J66: -0.266 | K66: 0.313
A67: Treasury Stock | B67: 0 | C67: 0 | D67: 0 | E67: 0 | F67: 0 | G67: 0 | H67: -4 | I67: -11.692 | J67: -19.507 | K67: -32.228
A68: Total Shareholders' Equity | B68: 7.500127 | C68: 10.376 | D68: 15.605 | E68: 33.885 | F68: 41.493 | G68: 58.131 | H68: 58.359 | I68: 59.646 | J68: 61.173 | K68: 59.142
A69: Total Equity | B69: 7.500127 | C69: 10.376 | D69: 15.605 | E69: 33.885 | F69: 41.493 | G69: 58.131 | H69: 58.359 | I69: 59.646 | J69: 61.173 | K69: 59.142
A70: Total Liabilities & Shareholders' Equity | B70: 17.584923 | C70: 21.984 | D70: 30.737 | E70: 55.126 | F70: 66.301 | G70: 99.178 | H70: 102.583 | I70: 102.806 | J70: 105.252 | K70: 115.449
A71: Per Share
A72: Book Value per Share | B72: 10.60149 | C72: 14.2137 | D72: 20.26623 | E72: 37.94513 | F72: 45.15016 | G72: 58.77755 | H72: 57.83845 | I72: 61.42739 | J72: 63.5894 | K72: 63.662
A73: Tangible Book Value per Share | B73: -1.495458 | C73: 2.861644 | D73: 0.881818 | E73: 4.509518 | F73: 12.035909 | G73: 1.229525 | H73: 2.64222 | I73: 5.91967 | J73: 5.677755 | K73: -6.043057
A74: All figures in billions of U.S. Dollar except per share items.

Sheet CRM-US-IS
A2: Salesforce, Inc. (CRM)
A5: Salesforce, Inc.
A6: CRM 79466L302 2310525 NYSE Common stock
A7: Source: FactSet Fundamentals
B8: JAN '17 | C8: JAN '18 | D8: JAN '19 | E8: JAN '20 | F8: JAN '21 | G8: JAN '22 | H8: JAN '23 | I8: JAN '24 | J8: JAN '25 | K8: JAN '26
C9: Restate
A10: Sales | B10: 8391.984 | C10: 10540 | D10: 13282 | E10: 17098 | F10: 21252 | G10: 26492 | H10: 31352 | I10: 34857 | J10: 37895 | K10: 41525
A11: Cost of Goods Sold (COGS) incl. D&A | B11: 2334.131 | C11: 2894 | D11: 3683 | E11: 4587 | F11: 5897 | G11: 7753 | H11: 9276 | I11: 9432 | J11: 9544 | K11: 10265
A12: COGS excluding D&A | B12: 1701.886 | C12: 2141 | D12: 2721 | E12: 2452 | F12: 3051 | G12: 4455 | H12: 5490 | I12: 5473 | J12: 6067 | K12: 6634
A13: Depreciation & Amortization Expense | B13: 632.245 | C13: 753 | D13: 962 | E13: 2135 | F13: 2846 | G13: 3298 | H13: 3786 | I13: 3959 | J13: 3477 | K13: 3631
A14: Depreciation | B14: 323.377 | C14: 466 | D14: 515 | E14: 1343 | F14: 1746 | G14: 1698 | H14: 1786 | I14: 2059 | J14: 1877 | K14: 1931
A15: Amortization of Intangibles | B15: 308.868 | C15: 287 | D15: 447 | E15: 792 | F15: 1100 | G15: 1600 | H15: 2000 | I15: 1900 | J15: 1600 | K15: 1700
A16: Gross Income | B16: 6057.853 | C16: 7646 | D16: 9599 | E16: 12511 | F16: 15355 | G16: 18739 | H16: 22076 | I16: 25425 | J16: 28351 | K16: 31260
A17: SG&A Expense | B17: 5980.616 | C17: 7192 | D17: 9037 | E17: 12008 | F17: 14900 | G17: 18191 | H17: 20218 | I17: 19426 | J17: 20685 | K17: 22343
A18: Research & Development | B18: 1208.127 | C18: 1553 | D18: 1886 | E18: 2766 | F18: 3598 | G18: 4465 | H18: 5055 | I18: 4906 | J18: 5493 | K18: 5993
A19: Other SG&A | B19: 4772.489 | C19: 5639 | D19: 7151 | E19: 9242 | F19: 11302 | G19: 13726 | H19: 15163 | I19: 14520 | J19: 15192 | K19: 16350
A20: EBIT (Operating Income) | B20: 77.237 | C20: 454 | D20: 562 | E20: 503 | F20: 455 | G20: 548 | H20: 1858 | I20: 5999 | J20: 7666 | K20: 8917
A21: Nonoperating Income - Net | B21: 138.873 | C21: 38 | D21: 568 | E21: 549 | F21: 2232 | G21: 286 | H21: 227 | I21: 257 | J21: 745 | K21: 543
... A23: Other Income (Expense) | B23: 116.972 | C23: 1 | D23: 507 | E23: 432 | F23: 2232 | G23: 286 | H23: 227 | I23: 257 | J23: 745 | K23: 4
A24: Interest Expense | B24: 88.988 | C24: 87 | D24: 154 | E24: 131 | F24: 126 | G24: 220 | H24: 287 | J24: 272 | K24: 324
A25: Gross Interest Expense | B25: 88.988 | C25: 87 | D25: 154 | E25: 131 | F25: 126 | G25: 220 | H25: 287 | J25: 272 | K25: 324
A26: Unusual Expense - Net | B26: 101.739 | C26: -15 | D26: -7 | E26: 215 | F26: 0 | G26: -918 | H26: 1138 | I26: 1306 | J26: 701 | K26: -384
A27: Impairments | G27: 51 | H27: 491 | I27: 466 | J27: 582 | K27: 496
A28: Financial Fixed Assets | G28: 51 | H28: 491 | I28: 466 | J28: 582 | K28: 496
A29: Restructuring Expense | B29: 15.5 | C29: 0 | D29: 27 | E29: 40 | F29: 0 | G29: 0 | H29: 828 | I29: 988 | J29: 461 | K29: 586
A30: Unrealized Valuation Gain/Loss | B30: -86.239 | C30: 15 | D30: 34 | E30: -9 | G30: 969 | H30: 181 | I30: 148 | J30: 342 | K30: 1466
A31: Investments | I31: 148 | J31: 342 | K31: 1466
A32: Hedges/Derivatives | B32: -86.239 | C32: 15 | D32: 34 | E32: -9 | G32: 969 | H32: 181
A33: Excpl Chrgs - Others | B33: 0 | E33: 166 | F33: 0 | G33: 0
A34: Early termination of Contracts costs (Income) | B34: 0 | E34: 166 | F34: 0 | G34: 0
A35: Pretax Income | B35: 25.383 | C35: 420 | D35: 983 | E35: 706 | F35: 2561 | G35: 1532 | H35: 660 | I35: 4950 | J35: 7438 | K35: 9520
A36: Income Taxes | B36: -154.249 | C36: 60 | D36: -127 | E36: 580 | F36: -1511 | G36: 88 | H36: 452 | I36: 814 | J36: 1241 | K36: 2063
A37: Income Taxes - Current Domestic | B37: 4.779 | C37: -5 | D37: 39 | E37: 545 | F37: 291 | G37: -10 | H37: 389 | I37: 1139 | J37: 1529 | K37: 485
A38: Income Taxes - Current Foreign | B38: 71.878 | C38: 85 | D38: 117 | E38: 8 | F38: -12 | G38: 352 | H38: 397 | I38: 417 | J38: 925 | K38: 619
A39: Income Taxes - Deferred Domestic | B39: -218.656 | C39: -16 | D39: -285 | E39: -33 | F39: 294 | G39: -238 | H39: -337 | I39: -822 | J39: -1149 | K39: 739
A40: Income Taxes - Deferred Foreign | B40: -12.25 | C40: -4 | D40: 2 | E40: 60 | F40: -2084 | G40: -16 | H40: 3 | I40: 80 | J40: -64 | K40: 220
A41: Consolidated Net Income | B41: 179.632 | C41: 360 | D41: 1110 | E41: 126 | F41: 4072 | G41: 1444 | H41: 208 | I41: 4136 | J41: 6197 | K41: 7457
A42: Net Income | B42: 179.632 | C42: 360 | D42: 1110 | E42: 126 | F42: 4072 | G42: 1444 | H42: 208 | I42: 4136 | J42: 6197 | K42: 7457
A43: Net Income available to Common | B43: 179.632 | C43: 360 | D43: 1110 | E43: 126 | F43: 4072 | G43: 1444 | H43: 208 | I43: 4136 | J43: 6197 | K43: 7457
A44: Per Share
A45: EPS (recurring) | B45: 0.358245 | C45: 0.47551 | D45: 1.425935 | E45: 0.325294 | F45: 4.378495 | G45: 0.822793 | H45: 1.007623 | I45: 5.132317 | J45: 6.866222 | K45: 7.519038
A46: EPS (basic) | B46: 0.26 | C46: 0.5 | D46: 1.48 | E46: 0.152 | F46: 4.4846 | G46: 1.512 | H46: 0.2097 | I46: 4.2464 | J46: 6.4418 | K46: 7.8495
A47: Basic Shares Outstanding | B47: 687.797 | C47: 715 | D47: 751 | E47: 829 | F47: 908 | G47: 955 | H47: 992 | I47: 974 | J47: 962 | K47: 950
A48: Total Shares Outstanding | B48: 707.46 | C48: 730 | D48: 770 | E48: 893 | F48: 919 | G48: 989 | H48: 1009 | I48: 971 | J48: 962 | K48: 929
A49: EPS (diluted) | B49: 0.26 | C49: 0.49 | D49: 1.43 | E49: 0.1482 | F49: 4.3785 | G49: 1.4826 | H49: 0.2086 | I49: 4.2032 | J49: 6.3624 | K49: 7.8002
A50: Diluted Shares Outstanding | B50: 700.217 | C50: 735 | D50: 775 | E50: 850 | F50: 930 | G50: 974 | H50: 997 | I50: 984 | J50: 974 | K50: 956
A51: Total Shares Outstanding | B51: 707.46 | C51: 730 | D51: 770 | E51: 893 | F51: 919 | G51: 989 | H51: 1009 | I51: 971 | J51: 962 | K51: 929
A52: Earnings Persistence | B52: 70.265 | C52: 88.73 | D52: 66.381 | E52: 68.402 | F52: 84.008 | G52: 69.737 | H52: 88.821 | I52: 88.373 | J52: 90.891 | K52: 86.583
A53: Dividends per Share | B53: 0 | C53: 0 | D53: 0 | E53: 0 | F53: 0 | G53: 0 | H53: 0 | I53: 0 | J53: 1.6 | K53: 1.664
A54: Payout Ratio | B54: 0 | C54: 0 | D54: 0 | E54: 0 | F54: 0 | G54: 0 | H54: 0 | I54: 0 | J54: 25.147743 | K54: 21.332786
A55: EBITDA
A56: EBITDA | B56: 709.482 | C56: 1207 | D56: 1524 | E56: 2638 | F56: 3301 | G56: 3846 | H56: 5644 | I56: 9958 | J56: 11143 | K56: 12548
A57: EBIT | B57: 77.237 | C57: 454 | D57: 562 | E57: 503 | F57: 455 | G57: 548 | H57: 1858 | I57: 5999 | J57: 7666 | K57: 8917
A58: Depreciation & Amortization Expense | B58: 632.245 | C58: 753 | D58: 962 | E58: 2135 | F58: 2846 | G58: 3298 | H58: 3786 | I58: 3959 | J58: 3477 | K58: 3631
A59: All figures in millions of U.S. Dollar except per share items.

Sheet CRM-US-CF
A2: Salesforce, Inc. (CRM)
A4: Salesforce, Inc.
A5: CRM 79466L302 2310525 NYSE Common stock
A6: Source: FactSet Fundamentals
B7: JAN '17 | C7: JAN '18 | D7: JAN '19 | E7: JAN '20 | F7: JAN '21 | G7: JAN '22 | H7: JAN '23 | I7: JAN '24 | J7: JAN '25 | K7: JAN '26
C8: Restate
A9: Operating Activities
A10: Net Income / Starting Line | B10: 179.632 | C10: 360 | D10: 1110 | E10: 126 | F10: 4072 | G10: 1444 | H10: 208 | I10: 4136 | J10: 6197 | K10: 7457
A11: Depreciation, Depletion & Amortization | B11: 632.245 | C11: 1345 | D11: 1699 | E11: 3011 | F11: 3904 | G11: 4646 | H11: 5454 | I11: 5884 | J11: 5572 | K11: 3631
A12: Depreciation and Depletion | B12: 323.377 | E12: 1343 | F12: 1746 | G12: 1698 | H12: 1786 | I12: 2059 | J12: 1877 | K12: 1931
A13: Amortization of Intangible Assets | B13: 308.868 | E13: 1668 | F13: 2158 | G13: 2948 | H13: 3668 | I13: 3825 | J13: 3695 | K13: 1700
A14: Other Funds | B14: 1208.752 | C14: 1009 | D14: 761 | E14: 1524 | F14: -1983 | G14: 1568 | H14: 3518 | I14: 3064 | J14: 3304 | K14: 4689
A15: Funds from Operations | B15: 2020.629 | C15: 2714 | D15: 3570 | E15: 4661 | F15: 5993 | G15: 7658 | H15: 9180 | I15: 13084 | J15: 15073 | K15: 15777
A16: Changes in Working Capital | B16: 141.569 | C16: 24 | D16: -172 | E16: -330 | F16: -1192 | G16: -1658 | H16: -2069 | I16: -2850 | J16: -1981 | K16: -781
A17: Receivables | B17: -628.477 | C17: -719 | D17: -923 | E17: -1000 | F17: -1556 | G17: -1824 | H17: -995 | I17: -659 | J17: -490 | K17: -2160
A18: Accounts Payable | C18: -39 | D18: 74 | E18: 15 | F18: 1100 | G18: 507 | H18: 528 | I18: -478 | J18: 1089 | K18: 1014
A19: Other Accruals | C19: 392 | D19: 213 | E19: 967
A20: Other Assets/Liabilities | B20: 770.046 | C20: 390 | D20: 464 | E20: -312 | F20: -736 | G20: -341 | H20: -1602 | I20: -1713 | J20: -2580 | K20: 365
A21: Net Operating Cash Flow | B21: 2162.198 | C21: 2738 | D21: 3398 | E21: 4331 | F21: 4801 | G21: 6000 | H21: 7111 | I21: 10234 | J21: 13092 | K21: 14996
A22: Investing Activities
A23: Capital Expenditures | B23: -463.958 | C23: -534 | D23: -595 | E23: -643 | F23: -710 | G23: -717 | H23: -798 | I23: -736 | J23: -658 | K23: -594
A24: Capital Expenditures (Fixed Assets) | B24: -463.958 | C24: -534 | D24: -595 | E24: -643 | F24: -710 | G24: -717 | H24: -798 | I24: -736 | J24: -658 | K24: -594
A25: Net Assets from Acquisitions | B25: -3192.739 | C25: -25 | D25: -5115 | E25: -369 | F25: -1281 | G25: -14876 | H25: -439 | I25: -82 | J25: -2734 | K25: -9268
A26: Purchase/Sale of Investments | B26: 972.356 | C26: -1452 | D26: 402 | E26: -1968 | F26: -1980 | G26: 1057 | H26: -752 | I26: -509 | J26: 229 | K26: 1272
A27: Purchase of Investments | B27: 1100.399 | C27: 2219 | D27: 1430 | E27: 4625 | F27: 5902 | G27: 7392 | H27: 5327 | I27: 4257 | J27: 7418 | K27: 5721
A28: Sale/Maturity of Investments | B28: 2072.755 | C28: 767 | D28: 1832 | E28: 2657 | F28: 3922 | G28: 8449 | H28: 4575 | I28: 3748 | J28: 7647 | K28: 6993
A29: Net Investing Cash Flow | B29: -2684.341 | C29: -2011 | D29: -5308 | E29: -2980 | F29: -3971 | G29: -14536 | H29: -1989 | I29: -1327 | J29: -3163 | K29: -8590
A30: Financing Activities
A31: Cash Dividends Paid | B31: 0 | C31: 0 | D31: 0 | E31: 0 | F31: 0 | G31: 0 | H31: 0 | I31: 0 | J31: -1537 | K31: -1587
A32: Common Dividends | B32: 0 | C32: 0 | D32: 0 | E32: 0 | F32: 0 | G32: 0 | H32: 0 | I32: 0 | J32: -1537 | K32: -1587
A33: Change in Capital Stock | B33: 401.481 | C33: 650 | D33: 704 | E33: 840 | F33: 1321 | G33: 1289 | H33: -3139 | I33: -5666 | J33: -6289 | K33: -11557
A34: Repurchase of Common & Preferred Stk. | B34: 0 | C34: 0 | D34: 0 | E34: 0 | F34: 0 | G34: 0 | H34: -4000 | I34: -7620 | J34: -7829 | K34: -12596
A35: Sale of Common & Preferred Stock | B35: 401.481 | C35: 650 | D35: 704 | E35: 840 | F35: 1321 | G35: 1289 | H35: 861 | I35: 1954 | J35: 1540 | K35: 1039
A36: Proceeds from Stock Options | B36: 401.481 | C36: 650 | D36: 704 | E36: 840 | F36: 1321 | G36: 1289 | H36: 861 | I36: 1954 | J36: 1540 | K36: 1039
A37: Issuance/Reduction of Debt, Net | B37: 596.217 | C37: -429 | D37: 1306 | E37: -676 | F37: -127 | G37: 6549 | H37: -423 | I37: -1811 | J37: -1603 | K37: 5416
A38: Change in Long-Term Debt | B38: 596.217 | C38: -429 | D38: 1306 | E38: -676 | F38: -127 | G38: 6549 | H38: -423 | I38: -1811 | J38: -1603 | K38: 5416
A39: Issuance of Long-Term Debt | B39: 1244.374 | C39: 0 | D39: 2966 | E39: 0 | F39: 0 | G39: 7906 | H39: 0 | I39: 0 | J39: 0 | K39: 6000
A40: Reduction in Long-Term Debt | B40: -648.157 | C40: -429 | D40: -1660 | E40: -676 | F40: -127 | G40: -1357 | H40: -423 | I40: -1811 | J40: -1603 | K40: -584
A41: Other Funds | B41: 0 | C41: 0 | D41: 0 | E41: 0 | F41: 0 | G41: 0 | H41: 0 | I41: 0 | J41: 0 | K41: -351
A42: Other Uses | B42: 0 | C42: 0 | D42: 0 | E42: 0 | F42: 0 | G42: 0 | H42: 0 | I42: 0 | J42: 0 | K42: -351
A43: Net Financing Cash Flow | B43: 997.698 | C43: 221 | D43: 2010 | E43: 164 | F43: 1194 | G43: 7838 | H43: -3562 | I43: -7477 | J43: -9429 | K43: -8079
A44: All Activities
A45: Exchange Rate Effect | B45: -27.369 | C45: -12 | D45: 26 | E45: -39 | F45: 26 | G45: -33 | H45: -8 | I45: 26 | J45: -124 | K45: 152
A46: Net Change in Cash | B46: 448.186 | C46: 936 | D46: 126 | E46: 1476 | F46: 2050 | G46: -731 | H46: 1552 | I46: 1456 | J46: 376 | K46: -1521
A47: Free Cash Flow | B47: 1698.24 | C47: 2204 | D47: 2803 | E47: 3688 | F47: 4091 | G47: 5283 | H47: 6313 | I47: 9498 | J47: 12434 | K47: 14402
A48: Free Cash Flow per Share | B48: 2.425305 | C48: 2.998639 | D48: 3.616774 | E48: 4.338824 | F48: 4.398925 | G48: 5.424025 | H48: 6.331996 | I48: 9.652439 | J48: 12.765914 | K48: 15.064854
A49: Free Cash Flow Yield (%) | B49: 3.066126 | C49: 2.632464 | D49: 2.379926 | E49: 2.379915 | F49: 1.950224 | G49: 2.33161 | H49: 3.769718 | I49: 3.433932 | J49: 3.736001 | K49: 7.096356
A50: All figures in millions of U.S. Dollar except per share items.

Sheet HUBS-US-BS
A2: HubSpot, Inc. (HUBS)
A4: HubSpot, Inc.
A5: HUBS 443573100 BR4T3B3 NYSE Common stock
A6: Source: FactSet Fundamentals
B7: DEC '16 | C7: DEC '17 | D7: DEC '18 | E7: DEC '19 | F7: DEC '20 | G7: DEC '21 | H7: DEC '22 | I7: DEC '23 | J7: DEC '24 | K7: DEC '25
I8: Restate
A9: Assets
A10: Cash & Short-Term Investments | B10: 114.512 | C10: 509.1 | D10: 597.425 | E10: 967.32 | F10: 1251.196 | G10: 1197.975 | H10: 1412.684 | I10: 1388.232 | J10: 2069.495 | K10: 1703.794
A11: Cash Only | B11: 59.864 | C11: 92.437 | D11: 116.664 | E11: 275.486 | F11: 378.123 | G11: 377.013 | H11: 331.022 | I11: 387.987 | J11: 512.667 | K11: 882.242
A12: Total Short Term Investments | B12: 54.648 | C12: 416.663 | D12: 480.761 | E12: 691.834 | F12: 873.073 | G12: 820.962 | H12: 1081.662 | I12: 1000.245 | J12: 1556.828 | K12: 821.552
A13: Short-Term Receivables | B13: 38.984 | C13: 60.676 | D13: 77.1 | E13: 92.517 | F13: 126.433 | G13: 157.362 | H13: 226.849 | I13: 295.303 | J13: 334.829 | K13: 419.146
A14: Accounts Receivables, Net | B14: 38.984 | C14: 60.676 | D14: 77.1 | E14: 92.517 | F14: 126.433 | G14: 157.362 | H14: 226.849 | I14: 295.303 | J14: 334.829 | K14: 419.146
A15: Accounts Receivables, Gross | B15: 39.601 | C15: 61.314 | D15: 78.417 | E15: 94.101 | F15: 128.426 | G15: 159.13 | H15: 230.115 | I15: 300.819 | J15: 340.917 | K15: 425.971
A16: Bad Debt/Doubtful Accounts | B16: -0.617 | C16: -0.638 | D16: -1.317 | E16: -1.584 | F16: -1.993 | G16: -1.768 | H16: -3.266 | I16: -5.516 | J16: -6.088 | K16: -6.825
A17: Other Current Assets | B17: 13.732 | C17: 19.382 | D17: 14.229 | E17: 17.809 | F17: 34.716 | G17: 38.388 | H17: 44.074 | I17: 88.679 | J17: 80.586 | K17: 100.611
A18: Prepaid Expenses | B18: 5.299 | C18: 4.964
A19: Miscellaneous Current Assets | B19: 8.433 | C19: 14.418 | D19: 14.229 | E19: 17.809 | F19: 34.716 | G19: 38.388 | H19: 44.074 | I19: 88.679 | J19: 80.586 | K19: 100.611
A20: Total Current Assets | B20: 167.228 | C20: 589.158 | D20: 688.754 | E20: 1077.646 | F20: 1412.345 | G20: 1393.725 | H20: 1683.607 | I20: 1772.214 | J20: 2484.91 | K20: 2223.551
A21: Net Property, Plant & Equipment | B21: 30.201 | C21: 43.294 | D21: 52.468 | E21: 318.039 | F21: 377.016 | G21: 376.962 | H21: 424.531 | I21: 354.402 | J21: 330.395 | K21: 342.69
A22: Property, Plant & Equipment - Gross | B22: 42.999 | C22: 65.52 | D22: 86.91 | E22: 367.118 | F22: 447.869 | G22: 463.589 | H22: 536.976 | I22: 499.758 | J22: 476.972 | K22: 518.545
A23: Construction in Progress | B23: 0.322 | C23: 3.198 | D23: 2.498 | E23: 23.714 | F23: 10.014 | G23: 4.141 | H23: 1.699 | I23: 0 | J23: 1.612 | K23: 5.582
A24: Leases | B24: 4.738 | C24: 3.45 | D24: 3.45 | E24: 3.45 | F24: 3.45
A25: Computer Software and Equipment | B25: 6.072 | C25: 11.723 | D25: 22.498 | E25: 34.627 | F25: 48.458 | G25: 68.37 | H25: 96.314 | I25: 115.307 | J25: 125.73 | K25: 167.829
A26: Other Property, Plant & Equipment | B26: 31.867 | C26: 47.149 | D26: 58.464 | E26: 70.937 | F26: 110.054 | G26: 110.25 | H26: 119.659 | I26: 133.38 | J26: 133.4 | K26: 144.313
A27: Operating Lease Right-of-Use Assets | E27: 234.39 | F27: 275.893 | G27: 280.828 | H27: 319.304 | I27: 251.071 | J27: 216.23 | K27: 200.821
A28: Accumulated Depreciation | B28: 12.798 | C28: 22.226 | D28: 34.442 | E28: 49.079 | F28: 70.853 | G28: 86.627 | H28: 112.445 | I28: 145.356 | J28: 146.577 | K28: 175.855
A29: Total Long-Term Investments | B29: 36.039 | C29: 31.741 | D29: 11.9 | E29: 61.205 | F29: 40.426 | G29: 198.424 | H29: 165.344 | I29: 370.856 | J29: 230.765 | K29: 262.429
A30: LT Investment - Affiliate Companies | B30: 0 | C30: 0 | D30: 0 | E30: 4.4 | F30: 6.7 | G30: 20.5 | H30: 49.4 | I30: 41.1 | J30: 72.5 | K30: 103.988
A31: Other Long-Term Investments | B31: 36.039 | C31: 31.741 | D31: 11.9 | E31: 56.805 | F31: 33.726 | G31: 177.924 | H31: 115.944 | I31: 329.756 | J31: 158.265 | K31: 158.441
A32: Intangible Assets | B32: 16.312 | C32: 30.022 | D32: 32.615 | E32: 58.795 | F32: 66.543 | G32: 97.498 | H32: 127.463 | I32: 322.306 | J32: 401.555 | K32: 540.471
A33: Goodwill | B33: 9.773 | C33: 14.95 | D33: 14.95 | E33: 30.25 | F33: 31.318 | G33: 47.075 | H33: 46.227 | I33: 173.761 | J33: 209.508 | K33: 291.452
A34: Other Intangible Assets | B34: 6.539 | C34: 15.072 | D34: 17.665 | E34: 28.545 | F34: 35.225 | G34: 50.423 | H34: 81.236 | I34: 148.545 | J34: 192.047 | K34: 249.019
A35: Other Assets | B35: 9.975 | C35: 17.96 | D35: 48.216 | E35: 53.583 | F35: 77.036 | G35: 108.245 | H35: 143.793 | I35: 251.614 | J35: 348.208 | K35: 485.01
A36: Deferred Charges | B36: 9.025 | C36: 13.343 | D36: 41.778 | E36: 51.188 | F36: 72.872 | G36: 102.53 | H36: 137.551 | I36: 221.52 | J36: 309.507 | K36: 445.175
A37: Tangible Other Assets | B37: 0.95 | C37: 4.617 | D37: 6.438 | E37: 2.395 | F37: 4.164 | G37: 5.715 | H37: 6.242 | I37: 30.094 | J37: 38.701 | K37: 39.835
A38: Total Assets | B38: 259.755 | C38: 712.175 | D38: 833.953 | E38: 1569.268 | F38: 1973.366 | G38: 2174.854 | H38: 2544.738 | I38: 3071.392 | J38: 3795.833 | K38: 3854.151
A39: Liabilities & Shareholders' Equity
A40: Current
A41: ST Debt & Curr. Portion LT Debt | B41: 0.796 | C41: 0 | D41: 0 | E41: 23.641 | F41: 37.857 | G41: 45.994 | H41: 35.928 | I41: 35.047 | J41: 490.877 | K41: 39.703
A42: Accounts Payable | B42: 4.35 | C42: 4.657 | D42: 7.81 | E42: 12.842 | F42: 13.54 | G42: 2.773 | H42: 20.883 | I42: 9.106 | J42: 3.649 | K42: 24.764
A43: Other Current Liabilities | B43: 122.237 | C43: 173.639 | D43: 229.199 | E43: 286.006 | F43: 394.104 | G43: 568.707 | H43: 704.842 | I43: 897.855 | J43: 1078.873 | K43: 1403.004
A44: Accrued Payroll | B44: 11.415 | C44: 16.329 | D44: 23.589 | E44: 26.318 | F44: 44.054 | G44: 63.836 | H44: 62.846 | I44: 131.631 | J44: 169.485 | K44: 231.198
A45: Miscellaneous Current Liabilities | B45: 110.822 | C45: 157.31 | D45: 205.61 | E45: 259.688 | F45: 350.05 | G45: 504.871 | H45: 641.996 | I45: 766.224 | J45: 909.388 | K45: 1171.806
A46: Total Current Liabilities | B46: 127.383 | C46: 178.296 | D46: 237.009 | E46: 322.489 | F46: 445.501 | G46: 617.474 | H46: 761.653 | I46: 942.008 | J46: 1573.399 | K46: 1467.471
A47: Long-Term
A48: Long-Term Debt | B48: 0.275 | C48: 298.447 | D48: 318.782 | E48: 584.78 | F48: 750.763 | G48: 666.974 | H48: 770.411 | I48: 752.767 | J48: 254.539 | K48: 222.602
A49: Long-Term Debt excl Lease Obligations | B49: 0 | C49: 298.447 | D49: 318.782 | E49: 340.564 | F49: 471.099 | G49: 383.101 | H49: 454.227 | I49: 456.206 | J49: 0 | K49: 0
A50: Capital and Operating Lease Obligations | B50: 0.275 | C50: 0 | D50: 0 | E50: 244.216 | F50: 279.664 | G50: 283.873 | H50: 316.184 | I50: 296.561 | J50: 254.539 | K50: 222.602
A51: Provision for Risks & Charges | B51: 0.591 | C51: 0 | D51: 0 | E51: 0 | F51: 0 | G51: 0 | H51: 0 | I51: 0 | J51: 0 | K51: 0
A52: Other Liabilities | B52: 12.806 | C52: 25.072 | D52: 33.521 | E52: 12.041 | F52: 14.447 | G52: 16.607 | H52: 20.45 | I52: 42.269 | J52: 59.609 | K52: 97.834
A53: Other Liabilities (excl. Deferred Income) | B53: 11.635 | C53: 22.795 | D53: 31.342 | E53: 8.983 | F53: 10.811 | G53: 12.134 | H53: 14.546 | I53: 36.459 | J53: 55.64 | K53: 89.339
A54: Deferred Income | B54: 1.171 | C54: 2.277 | D54: 2.179 | E54: 3.058 | F54: 3.636 | G54: 4.473 | H54: 5.904 | I54: 5.81 | J54: 3.969 | K54: 8.495
A55: Total Liabilities | B55: 141.055 | C55: 501.815 | D55: 589.312 | E55: 919.31 | F55: 1210.711 | G55: 1301.055 | H55: 1552.514 | I55: 1737.044 | J55: 1887.547 | K55: 1787.907
A56: Equity
A57: Common Equity | B57: 118.7 | C57: 210.36 | D57: 244.641 | E57: 649.958 | F57: 762.655 | G57: 873.799 | H57: 992.224 | I57: 1334.348 | J57: 1908.286 | K57: 2066.244
A58: Common Stock Par/Carry Value | B58: 0.036 | C58: 0.038 | D58: 0.04 | E58: 0.044 | F58: 0.046 | G58: 0.047 | H58: 0.049 | I58: 0.05 | J58: 0.052 | K58: 0.053
A59: Additional Paid-In Capital/Capital Surplus | B59: 365.444 | C59: 496.461 | D59: 589.708 | E59: 1048.38 | F59: 1241.167 | G59: 1436.089 | H59: 1647.446 | I59: 2136.908 | J59: 2713.697 | K59: 2814.843
A60: Retained Earnings | B60: -245.916 | C60: -286.082 | D60: -344.384 | E60: -398.13 | F60: -483.161 | G60: -560.998 | H60: -642.381 | I60: -804.437 | J60: -799.809 | K60: -753.898
A61: Cumulative Translation Adjustment/Unrealized For. Exch. Gain | B61: -0.589 | C61: 0.379 | D61: -0.397 | E61: -0.61 | F61: 4.18 | G61: -0.532 | H61: -3.07 | I61: 0.95 | J61: -5.928 | K61: 3.426
A62: Unrealized Gain/Loss Marketable Securities | B62: -0.275 | C62: -0.436 | D62: -0.326 | E62: 0.274 | F62: 0.423 | G62: -0.807 | H62: -9.82 | I62: 0.877 | J62: 1.195 | K62: 1.289
A63: Other Appropriated Reserves | I63: 0 | J63: -0.921 | K63: 0.529
A64: Treasury Stock | B64: 0 | C64: 0 | D64: 0 | E64: 0 | F64: 0 | G64: 0 | H64: 0 | I64: 0 | J64: 0 | K64: 0.002
A65: Total Shareholders' Equity | B65: 118.7 | C65: 210.36 | D65: 244.641 | E65: 649.958 | F65: 762.655 | G65: 873.799 | H65: 992.224 | I65: 1334.348 | J65: 1908.286 | K65: 2066.244
A66: Total Equity | B66: 118.7 | C66: 210.36 | D66: 244.641 | E66: 649.958 | F66: 762.655 | G66: 873.799 | H66: 992.224 | I66: 1334.348 | J66: 1908.286 | K66: 2066.244
A67: Total Liabilities & Shareholders' Equity | B67: 259.755 | C67: 712.175 | D67: 833.953 | E67: 1569.268 | F67: 1973.366 | G67: 2174.854 | H67: 2544.738 | I67: 3071.392 | J67: 3795.833 | K67: 3854.151
A68: Per Share
A69: Book Value per Share | B69: 3.31712 | C69: 5.60915 | D69: 6.22496 | E69: 15.13114 | F69: 16.53811 | G69: 18.43847 | H69: 20.16019 | I69: 26.44997 | J69: 36.86298 | K69: 39.31584
A70: Tangible Book Value per Share | B70: 2.861279 | C70: 4.808629 | D70: 5.395064 | E70: 13.762379 | F70: 15.095132 | G70: 16.381114 | H70: 17.570372 | I70: 20.061093 | J70: 29.106013 | K70: 29.031928
A71: All figures in millions of U.S. Dollar except per share items.

Sheet HUBS-US-IS
A2: HubSpot, Inc. (HUBS)
A4: HubSpot, Inc.
A5: HUBS 443573100 BR4T3B3 NYSE Common stock
A6: Source: FactSet Fundamentals
B7: DEC '16 | C7: DEC '17 | D7: DEC '18 | E7: DEC '19 | F7: DEC '20 | G7: DEC '21 | H7: DEC '22 | I7: DEC '23 | J7: DEC '24 | K7: DEC '25
I8: Restate
A9: Sales | B9: 270.967 | C9: 375.612 | D9: 512.98 | E9: 674.86 | F9: 883.026 | G9: 1300.658 | H9: 1730.969 | I9: 2170.23 | J9: 2627.543 | K9: 3131.244
A10: Cost of Goods Sold (COGS) incl. D&A | B10: 61.865 | C10: 75.729 | D10: 100.357 | E10: 129.958 | F10: 166.959 | G10: 258.857 | H10: 314.259 | I10: 338.362 | J10: 393.265 | K10: 508.487
A11: COGS excluding D&A | B11: 50.688 | C11: 59.943 | D11: 76.929 | E11: 100.158 | F11: 127.759 | G11: 210.657 | H11: 251.859 | I11: 258.262 | J11: 279.665 | K11: 343.987
A12: Depreciation & Amortization Expense | B12: 11.177 | C12: 15.786 | D12: 23.428 | E12: 29.8 | F12: 39.2 | G12: 48.2 | H12: 62.4 | I12: 80.1 | J12: 113.6 | K12: 164.5
A13: Depreciation | B13: 5.9 | C13: 9.4 | D13: 12.828 | E13: 15 | F13: 20.6 | G13: 23.9 | H13: 27.8 | I13: 29 | J13: 29.7 | K13: 34.5
A14: Amortization of Intangibles | B14: 5.277 | C14: 6.386 | D14: 10.6 | E14: 14.8 | F14: 18.6 | G14: 24.3 | H14: 34.6 | I14: 51.1 | J14: 83.9 | K14: 130
A15: Gross Income | B15: 209.102 | C15: 299.883 | D15: 412.623 | E15: 544.902 | F15: 716.067 | G15: 1041.801 | H15: 1416.71 | I15: 1831.868 | J15: 2234.278 | K15: 2622.757
A16: SG&A Expense | B16: 253.764 | C16: 340.019 | D16: 460.881 | E16: 591.366 | F16: 766.895 | G16: 1094.408 | H16: 1525.811 | I16: 1935.954 | J16: 2297.89 | K16: 2611.364
A17: Research & Development | B17: 45.997 | C17: 70.373 | D17: 117.603 | E17: 158.237 | F17: 205.589 | G17: 301.97 | H17: 442.022 | I17: 617.745 | J17: 778.714 | K17: 905.943
A18: Other SG&A | B18: 207.767 | C18: 269.646 | D18: 343.278 | E18: 433.129 | F18: 561.306 | G18: 792.438 | H18: 1083.789 | I18: 1318.209 | J18: 1519.176 | K18: 1705.421
A19: EBIT (Operating Income) | B19: -44.662 | C19: -40.136 | D19: -48.258 | E19: -46.464 | F19: -50.828 | G19: -52.607 | H19: -109.101 | I19: -104.086 | J19: -63.612 | K19: 11.393
A20: Nonoperating Income - Net | B20: -0.102 | C20: 3.278 | D20: 7.684 | E20: 19.036 | F20: 7.062 | G20: -6.946 | H20: -1.893 | I20: 54.155 | J20: 82.357 | K20: 60.863
... A24: Gross Interest Expense | B24: 0.265 | C24: 13.181 | D24: 21.386 | E24: 22.818 | F24: 37.049 | G24: 25.39 | H24: 3.762 | I24: 3.801 | J24: 3.721 | K24: 0.876
A25: Unusual Expense - Net | E25: 0.527 | G25: -11.125 | H25: -10.064 | I25: 96.843 | J25: -13.653 | K25: 1.917
A26: Impairments | H26: -5.863 | J26: 3.602 | K26: 5.923
A27: Financial Fixed Assets | H27: -5.863 | J27: 3.602 | K27: 5.923
A28: Restructuring Expense | B28: 0 | C28: 0 | D28: 0 | E28: 0.527 | F28: 0 | G28: -4.276 | H28: 0 | I28: 96.843 | J28: 3.99 | K28: 4.036
A29: Unrealized Valuation Gain/Loss | G29: 11.741 | H29: 4.201 | J29: 21.245 | K29: 8.042
A30: Investments | G30: 11.741 | H30: 4.201 | J30: 21.245 | K30: 5.5
A31: Hedges/Derivatives | K31: 2.542
A32: Excpl Chrgs - Others | G32: 4.892 | H32: 0
A33: Restructuring of Debt | G33: 4.892 | H33: 0
A34: Pretax Income | B34: -45.029 | C34: -50.039 | D34: -61.96 | E34: -50.773 | F34: -80.815 | G34: -73.818 | H34: -104.692 | I34: -150.575 | J34: 28.677 | K34: 69.463
A35: Income Taxes | B35: 0.533 | C35: -10.325 | D35: 1.868 | E35: 2.973 | F35: 4.216 | G35: 4.019 | H35: 8.057 | I35: 13.935 | J35: 24.049 | K35: 23.552
A36: Income Taxes - Current Domestic | B36: 0.095 | C36: 0.144 | D36: 0.324 | E36: 0.479 | F36: 0.893 | G36: 1.279 | H36: 2.401 | I36: 1.965 | J36: 9.271 | K36: 5.754
A37: Income Taxes - Current Foreign | B37: 0.579 | C37: 1.077 | D37: 1.508 | E37: 3.293 | F37: 5.508 | G37: 5.609 | H37: 7.778 | I37: 11.42 | J37: 12.088 | K37: 17.8
A38: Income Taxes - Deferred Domestic | B38: -0.061 | C38: -11.412 | D38: -0.021 | E38: -0.16 | F38: 0.116 | G38: -0.989 | H38: 0 | I38: 0 | J38: 0.384 | K38: 1.606
A39: Income Taxes - Deferred Foreign | B39: -0.08 | C39: -0.134 | D39: 0.057 | E39: -0.639 | F39: -2.301 | G39: -1.88 | H39: -2.122 | I39: 0.55 | J39: 2.306 | K39: -1.608
A40: Consolidated Net Income | B40: -45.562 | C40: -39.714 | D40: -63.828 | E40: -53.746 | F40: -85.031 | G40: -77.837 | H40: -112.749 | I40: -164.51 | J40: 4.628 | K40: 45.911
A41: Net Income | B41: -45.562 | C41: -39.714 | D41: -63.828 | E41: -53.746 | F41: -85.031 | G41: -77.837 | H41: -112.749 | I41: -164.51 | J41: 4.628 | K41: 45.911
A42: Net Income available to Common | B42: -45.562 | C42: -39.714 | D42: -63.828 | E42: -53.746 | F42: -85.031 | G42: -77.837 | H42: -112.749 | I42: -164.51 | J42: 4.628 | K42: 45.911
A43: Per Share
A44: EPS (recurring) | B44: -1.294485 | C44: -1.078394 | D44: -1.656622 | E44: -1.270127 | F44: -1.899837 | G44: -1.826033 | H44: -2.492329 | I44: -1.939168 | J44: -0.095121 | K44: 0.888313
A45: EPS (basic) | B45: -1.29 | C45: -1.08 | D45: -1.6566 | E45: -1.2789 | F45: -1.8998 | G45: -1.66 | H45: -2.3458 | I45: -3.2983 | J45: 0.0904 | K45: 0.8752
A46: Basic Shares Outstanding | B46: 35.197 | C46: 36.827 | D46: 38.529 | E46: 42.025 | F46: 44.757 | G46: 46.891 | H46: 48.065 | I46: 49.877 | J46: 51.178 | K46: 52.455
A47: Total Shares Outstanding | B47: 35.784 | C47: 37.503 | D47: 39.3 | E47: 42.955 | F47: 46.115 | G47: 47.39 | H47: 49.217 | I47: 50.448 | J47: 51.767 | K47: 52.555
A48: EPS (diluted) | B48: -1.29 | C48: -1.08 | D48: -1.6566 | E48: -1.2789 | F48: -1.8998 | G48: -1.66 | H48: -2.3458 | I48: -3.2983 | J48: 0.0893 | K48: 0.8631
A49: Diluted Shares Outstanding | B49: 35.197 | C49: 36.827 | D49: 38.529 | E49: 42.025 | F49: 44.757 | G49: 46.891 | H49: 48.065 | I49: 49.877 | J49: 51.819 | K49: 53.194
A50: Total Shares Outstanding | B50: 35.784 | C50: 37.503 | D50: 39.3 | E50: 42.955 | F50: 46.115 | G50: 47.39 | H50: 49.217 | I50: 50.448 | J50: 51.767 | K50: 52.555
A51: Earnings Persistence | B51: 23.516 | C51: 0 | D51: 10.263 | E51: 32.686 | F51: 85.382 | G51: 71.43 | H51: 85.076 | I51: 65.713 | J51: 79.245 | K51: 49.344
A52: EBITDA
A53: EBITDA | B53: -33.485 | C53: -24.35 | D53: -24.83 | E53: -16.664 | F53: -11.628 | G53: -4.407 | H53: -46.701 | I53: -23.986 | J53: 49.988 | K53: 175.893
A54: EBIT | B54: -44.662 | C54: -40.136 | D54: -48.258 | E54: -46.464 | F54: -50.828 | G54: -52.607 | H54: -109.101 | I54: -104.086 | J54: -63.612 | K54: 11.393
A55: Depreciation & Amortization Expense | B55: 11.177 | C55: 15.786 | D55: 23.428 | E55: 29.8 | F55: 39.2 | G55: 48.2 | H55: 62.4 | I55: 80.1 | J55: 113.6 | K55: 164.5
A56: All figures in millions of U.S. Dollar except per share items.

Sheet HUBS-US-CF
A2: HubSpot, Inc. (HUBS)
A4: HubSpot, Inc.
A5: HUBS 443573100 BR4T3B3 NYSE Common stock
A6: Source: FactSet Fundamentals
B7: DEC '16 | C7: DEC '17 | D7: DEC '18 | E7: DEC '19 | F7: DEC '20 | G7: DEC '21 | H7: DEC '22 | I7: DEC '23 | J7: DEC '24 | K7: DEC '25
I8: Restate
A9: Operating Activities
A10: Net Income / Starting Line | B10: -45.562 | C10: -39.714 | D10: -63.828 | E10: -53.746 | F10: -85.031 | G10: -77.837 | H10: -112.749 | I10: -164.51 | J10: 4.628 | K10: 45.911
A11: Depreciation, Depletion & Amortization | B11: 11.177 | C11: 15.786 | D11: 23.428 | E11: 28.793 | F11: 37.06 | G11: 45.159 | H11: 58.15 | I11: 72.673 | J11: 96.828 | K11: 136.295
A12: Depreciation and Depletion | B12: 5.9 | C12: 9.4 | D12: 12.828 | E12: 13.993 | G12: 20.859 | H12: 23.55 | I12: 21.573 | J12: 12.928 | K12: 6.295
A13: Amortization of Intangible Assets | B13: 5.277 | C13: 6.386 | D13: 10.6 | E13: 14.8 | G13: 24.3 | H13: 34.6 | I13: 51.1 | J13: 83.9 | K13: 130
A14: Deferred Taxes & Investment Tax Credit | B14: -0.133 | C14: -11.546 | D14: 0.036 | E14: -0.799 | F14: -2.185 | G14: -2.869 | H14: -2.122 | I14: 0.55 | J14: 2.69 | K14: -0.002
A15: Deferred Taxes | B15: -0.133 | C15: -11.546 | D15: 0.036 | E15: -0.799 | F15: -2.185 | G15: -2.869 | H15: -2.122 | I15: 0.55 | J15: 2.69 | K15: -0.002
A16: Other Funds | B16: 37.371 | C16: 63.007 | D16: 92.628 | E16: 105.228 | F16: 103.228 | G16: 164.762 | H16: 271.416 | I16: 459.976 | J16: 437.617 | K16: 482.993
A17: Funds from Operations | B17: 2.853 | C17: 27.533 | D17: 52.264 | E17: 79.476 | F17: 53.072 | G17: 129.215 | H17: 214.695 | I17: 368.689 | J17: 541.763 | K17: 665.197
A18: Changes in Working Capital | B18: 16.513 | C18: 22.081 | D18: 32.587 | E18: 39.497 | F18: 35.841 | G18: 109.513 | H18: 58.479 | I18: -17.718 | J18: 56.836 | K18: 95.52
A19: Receivables | B19: -14.099 | C19: -20.18 | D19: -17.726 | E19: -15.428 | F19: -29.971 | G19: -34.107 | H19: -73.985 | I19: -57.618 | J19: -48.428 | K19: -64.003
A20: Accounts Payable | B20: 0.983 | C20: 1.1 | D20: 3.298 | E20: 3.927 | F20: 3.697 | G20: -10.608 | H20: 18.277 | I20: -14.031 | J20: -4.577 | K20: 18.999
A21: Other Accruals | B21: 3.897 | C21: 11.754 | D21: 17.719 | E21: 7.819 | F21: 26.02 | G21: 58.209 | H21: 32.375 | I21: 79.947 | J21: 89.129 | K21: 117.971
A22: Other Assets/Liabilities | B22: 25.732 | C22: 29.407 | D22: 29.296 | E22: 43.179 | F22: 36.095 | G22: 96.019 | H22: 81.812 | I22: -26.016 | J22: 20.712 | K22: 22.553
A23: Net Operating Cash Flow | B23: 19.366 | C23: 49.614 | D23: 84.851 | E23: 118.973 | F23: 88.913 | G23: 238.728 | H23: 273.174 | I23: 350.971 | J23: 598.599 | K23: 760.717
A24: Investing Activities
A25: Capital Expenditures | B25: -21.538 | C25: -36.762 | D25: -33.473 | E25: -53.846 | F25: -58.873 | G25: -61.865 | H25: -91.771 | I25: -100.254 | J25: -128.806 | K25: -184.063
A26: Capital Expenditures (Fixed Assets) | B26: -15.789 | C26: -20.276 | D26: -22.305 | E26: -40.372 | F26: -37.274 | G26: -28.726 | H26: -37.426 | I26: -33.718 | J26: -37.939 | K26: -53.165
A27: Capital Expenditures (Other Assets) | B27: -5.749 | C27: -16.486 | D27: -11.168 | E27: -13.474 | F27: -21.599 | G27: -33.139 | H27: -54.345 | I27: -66.536 | J27: -90.867 | K27: -130.898
A28: Net Assets from Acquisitions | B28: 0 | C28: -3.5 | D28: -0.5 | E28: -23.314 | F28: 0 | G28: -16.81 | H28: 0 | I28: -142.129 | J28: -40.438 | K28: -87.608
A29: Purchase/Sale of Investments | B29: -1.419 | C29: -360.935 | D29: -37.257 | E29: -239.034 | F29: -156.694 | G29: -100.833 | H29: -227.887 | I29: -92.383 | J29: -348.55 | K29: 763.444
A30: Purchase of Investments | B30: 52.259 | C30: 894.595 | D30: 681.632 | E30: 1305.4 | F30: 1519.857 | G30: 1500.951 | H30: 1537.391 | I30: 1594.917 | J30: 2009.148 | K30: 1476.681
A31: Sale/Maturity of Investments | B31: 50.84 | C31: 533.66 | D31: 644.375 | E31: 1066.366 | F31: 1363.163 | G31: 1400.118 | H31: 1309.504 | I31: 1502.534 | J31: 1660.598 | K31: 2240.125
A32: Other Funds | B32: 0 | C32: 0 | D32: 0 | E32: 0 | F32: 0 | G32: 0 | H32: 0 | I32: 0 | J32: 1.933 | K32: 0
A33: Other Sources | E33: 0 | F33: 0 | G33: 0 | H33: 0 | I33: 0 | J33: 1.933 | K33: 0
A34: Net Investing Cash Flow | B34: -22.957 | C34: -401.197 | D34: -71.23 | E34: -316.194 | F34: -215.567 | G34: -179.508 | H34: -319.658 | I34: -334.766 | J34: -515.861 | K34: 491.773
A35: Financing Activities
A36: Change in Capital Stock | B36: 11.584 | C36: 13.086 | D36: 21.555 | E36: 366.206 | F36: 30.371 | G36: 46.51 | H36: 39.931 | I36: 47.738 | J36: 75.501 | K36: -428.625
A37: Repurchase of Common & Preferred Stk. | B37: 0 | C37: 0 | D37: 0 | E37: 0 | F37: 0 | G37: 0 | H37: 0 | I37: 0 | J37: 0 | K37: -500.019
A38: Sale of Common & Preferred Stock | B38: 11.584 | C38: 13.086 | D38: 21.555 | E38: 366.206 | F38: 30.371 | G38: 46.51 | H38: 39.931 | I38: 47.738 | J38: 75.501 | K38: 71.394
A39: Proceeds from Sale of Stock | B39: 0 | C39: 0 | D39: 0 | E39: 342.628 | F39: 0 | G39: 0 | H39: 0 | I39: 0 | J39: 0 | K39: 0
A40: Proceeds from Stock Options | B40: 11.584 | C40: 13.086 | D40: 21.555 | E40: 23.578 | F40: 30.371 | G40: 46.51 | H40: 39.931 | I40: 47.738 | J40: 75.501 | K40: 71.394
A41: Issuance/Reduction of Debt, Net | B41: -0.743 | C41: 368.139 | D41: -0.744 | E41: -0.617 | F41: 199.513 | G41: -80.54 | H41: -20.977 | I41: -0.013 | J41: -0.057 | K41: -459.811
A42: Change in Current Debt | B42: 0 | C42: 0 | D42: 0 | E42: -0.284 | F42: -0.028 | G42: 0 | H42: 0 | I42: 0 | J42: 0 | K42: -459.811
A43: Change in Long-Term Debt | B43: -0.743 | C43: 368.139 | D43: -0.744 | E43: -0.333 | F43: 199.541 | G43: -80.54 | H43: -20.977 | I43: -0.013 | J43: -0.057 | K43: 0
A44: Issuance of Long-Term Debt | B44: 0 | C44: 448.113 | D44: 0 | E44: 0 | F44: 813.677 | G44: 8.985 | H44: 60.483 | I44: 0 | J44: 0 | K44: 0
A45: Reduction in Long-Term Debt | B45: -0.743 | C45: -79.974 | D45: -0.744 | E45: -0.333 | F45: -614.136 | G45: -89.525 | H45: -81.46 | I45: -0.013 | J45: -0.057 | K45: 0
A46: Other Funds | B46: -2.368 | C46: -4.419 | D46: -8.033 | E46: -6.247 | F46: -7.424 | G46: -17.439 | H46: -11.526 | I46: -10.714 | J46: -21.949 | K46: -21.573
A47: Other Uses | B47: -2.368 | C47: -4.419 | D47: -8.033 | E47: -6.247 | F47: -7.424 | G47: -17.439 | H47: -11.526 | I47: -10.714 | J47: -21.949 | K47: -21.573
A48: Net Financing Cash Flow | B48: 8.473 | C48: 376.806 | D48: 12.778 | E48: 359.342 | F48: 222.46 | G48: -51.469 | H48: 7.428 | I48: 37.011 | J48: 53.495 | K48: -910.009
A49: All Activities
A50: Exchange Rate Effect | B50: -0.76 | C50: 2.755 | D50: -2.069 | E50: -0.72 | F50: 6.831 | G50: -8.861 | H50: -6.811 | I50: 4.649 | J50: -11.553 | K50: 25.744
A51: Net Change in Cash | B51: 4.122 | C51: 27.978 | D51: 24.33 | E51: 161.401 | F51: 102.637 | G51: -1.11 | H51: -45.867 | I51: 57.865 | J51: 124.68 | K51: 368.225
A52: Free Cash Flow | B52: 3.577 | C52: 29.338 | D52: 62.546 | E52: 78.601 | F52: 51.639 | G52: 210.002 | H52: 235.748 | I52: 317.253 | J52: 560.66 | K52: 707.552
A53: Free Cash Flow per Share | B53: 0.101628 | C53: 0.796644 | D53: 1.623349 | E53: 1.870339 | F53: 1.153764 | G53: 4.478514 | H53: 4.904775 | I53: 6.360707 | J53: 10.819584 | K53: 13.30135
A54: Free Cash Flow Yield (%) | B54: 0.21623 | C54: 0.901181 | D54: 1.291139 | E54: 1.180025 | F54: 0.291031 | G54: 0.679438 | H54: 1.696391 | I54: 1.095654 | J54: 1.55282 | K54: 3.314565
A55: All figures in millions of U.S. Dollar except per share items.
